Workbook

Sheet Summary
A1: Dataiku DSS Diagnosis - Checklist Review Summary
A3: Bundle | B3: dku_diagnosis_2026-07-22-08-21-05 (Users/boonleeeu/.../Configs/)
A4: Diagnosis taken | B4: 2026-07-22 08:21 UTC
A5: Node | B5: Design node p4d, installid GbpIpatzv3MFrFfE6MwSlXCg, host gcp9234prdapp04 (GCP VM)
A6: DSS version | B6: 14.4.3 (latest GA: 15.0.2, 24 Sep 2026)
A7: Host | B7: RHEL 8.10, 8 vCPU (AMD EPYC 7B13), ~62GB RAM, no swap; DATA_DIR on 800GB LVM (74% used)
A8: Compute | B8: Spark + containerized execution on manual K8s cluster "P4D" (GKE); 25 users; SSO via Azure AD OIDC
A9: Generated | B9: 2026-09-25
A10: Reviewer | B10: Claude (AI-assisted review) - bundle dku_diagnosis_2026-07-22-08-21-05 (node p4d, DSS 14.4.3)
A12: Overall status counts
A13: Status | B13: All items | C13: Must-have | D13: Nice-to-have
A14: Pass | B14: =COUNTIF('Architecture, Compute & Infrast'!V:V,$A14)+COUNTIF('Enterprise-grade Security, Perm'!V:V,$A14)+COUNTIF('Generative AI Acceleration & In'!V:V,$A14)+COUNTIF('Scalable Performance, Stability'!V:V,$A14)+COUNTIF('Advanced Security Options (DSS '!V:V,$A14) -> 15 | C14: =COUNTIFS('Architecture, Compute & Infrast'!V:V,$A14,'Architecture, Compute & Infrast'!B:B,"must_have")+COUNTIFS('Enterprise-grade Security, Perm'!V:V,$A14,'Enterprise-grade Security, Perm'!B:B,"must_have")+COUNTIFS('Generative AI Acceleration & In'!V:V,$A14,'Generative AI Acceleration & In'!B:B,"must_have")+COUNTIFS('Scalable Performance, Stability'!V:V,$A14,'Scalable Performance, Stability'!B:B,"must_have")+COUNTIFS('Advanced Security Options (DSS '!V:V,$A14,'Advanced Security Options (DSS '!B:B,"must_have") -> 9 | D14: =COUNTIFS('Architecture, Compute & Infrast'!V:V,$A14,'Architecture, Compute & Infrast'!B:B,"nice_to_have")+COUNTIFS('Enterprise-grade Security, Perm'!V:V,$A14,'Enterprise-grade Security, Perm'!B:B,"nice_to_have")+COUNTIFS('Generative AI Acceleration & In'!V:V,$A14,'Generative AI Acceleration & In'!B:B,"nice_to_have")+COUNTIFS('Scalable Performance, Stability'!V:V,$A14,'Scalable Performance, Stability'!B:B,"nice_to_have")+COUNTIFS('Advanced Security Options (DSS '!V:V,$A14,'Advanced Security Options (DSS '!B:B,"nice_to_have") -> 6
A15: Fail | B15: =COUNTIF('Architecture, Compute & Infrast'!V:V,$A15)+COUNTIF('Enterprise-grade Security, Perm'!V:V,$A15)+COUNTIF('Generative AI Acceleration & In'!V:V,$A15)+COUNTIF('Scalable Performance, Stability'!V:V,$A15)+COUNTIF('Advanced Security Options (DSS '!V:V,$A15) -> 21 | C15: =COUNTIFS('Architecture, Compute & Infrast'!V:V,$A15,'Architecture, Compute & Infrast'!B:B,"must_have")+COUNTIFS('Enterprise-grade Security, Perm'!V:V,$A15,'Enterprise-grade Security, Perm'!B:B,"must_have")+COUNTIFS('Generative AI Acceleration & In'!V:V,$A15,'Generative AI Acceleration & In'!B:B,"must_have")+COUNTIFS('Scalable Performance, Stability'!V:V,$A15,'Scalable Performance, Stability'!B:B,"must_have")+COUNTIFS('Advanced Security Options (DSS '!V:V,$A15,'Advanced Security Options (DSS '!B:B,"must_have") -> 14 | D15: =COUNTIFS('Architecture, Compute & Infrast'!V:V,$A15,'Architecture, Compute & Infrast'!B:B,"nice_to_have")+COUNTIFS('Enterprise-grade Security, Perm'!V:V,$A15,'Enterprise-grade Security, Perm'!B:B,"nice_to_have")+COUNTIFS('Generative AI Acceleration & In'!V:V,$A15,'Generative AI Acceleration & In'!B:B,"nice_to_have")+COUNTIFS('Scalable Performance, Stability'!V:V,$A15,'Scalable Performance, Stability'!B:B,"nice_to_have")+COUNTIFS('Advanced Security Options (DSS '!V:V,$A15,'Advanced Security Options (DSS '!B:B,"nice_to_have") -> 7
A16: Partial | B16: =COUNTIF('Architecture, Compute & Infrast'!V:V,$A16)+COUNTIF('Enterprise-grade Security, Perm'!V:V,$A16)+COUNTIF('Generative AI Acceleration & In'!V:V,$A16)+COUNTIF('Scalable Performance, Stability'!V:V,$A16)+COUNTIF('Advanced Security Options (DSS '!V:V,$A16) -> 8 | C16: =COUNTIFS('Architecture, Compute & Infrast'!V:V,$A16,'Architecture, Compute & Infrast'!B:B,"must_have")+COUNTIFS('Enterprise-grade Security, Perm'!V:V,$A16,'Enterprise-grade Security, Perm'!B:B,"must_have")+COUNTIFS('Generative AI Acceleration & In'!V:V,$A16,'Generative AI Acceleration & In'!B:B,"must_have")+COUNTIFS('Scalable Performance, Stability'!V:V,$A16,'Scalable Performance, Stability'!B:B,"must_have")+COUNTIFS('Advanced Security Options (DSS '!V:V,$A16,'Advanced Security Options (DSS '!B:B,"must_have") -> 3 | D16: =COUNTIFS('Architecture, Compute & Infrast'!V:V,$A16,'Architecture, Compute & Infrast'!B:B,"nice_to_have")+COUNTIFS('Enterprise-grade Security, Perm'!V:V,$A16,'Enterprise-grade Security, Perm'!B:B,"nice_to_have")+COUNTIFS('Generative AI Acceleration & In'!V:V,$A16,'Generative AI Acceleration & In'!B:B,"nice_to_have")+COUNTIFS('Scalable Performance, Stability'!V:V,$A16,'Scalable Performance, Stability'!B:B,"nice_to_have")+COUNTIFS('Advanced Security Options (DSS '!V:V,$A16,'Advanced Security Options (DSS '!B:B,"nice_to_have") -> 5
A17: Needs Review | B17: =COUNTIF('Architecture, Compute & Infrast'!V:V,$A17)+COUNTIF('Enterprise-grade Security, Perm'!V:V,$A17)+COUNTIF('Generative AI Acceleration & In'!V:V,$A17)+COUNTIF('Scalable Performance, Stability'!V:V,$A17)+COUNTIF('Advanced Security Options (DSS '!V:V,$A17) -> 12 | C17: =COUNTIFS('Architecture, Compute & Infrast'!V:V,$A17,'Architecture, Compute & Infrast'!B:B,"must_have")+COUNTIFS('Enterprise-grade Security, Perm'!V:V,$A17,'Enterprise-grade Security, Perm'!B:B,"must_have")+COUNTIFS('Generative AI Acceleration & In'!V:V,$A17,'Generative AI Acceleration & In'!B:B,"must_have")+COUNTIFS('Scalable Performance, Stability'!V:V,$A17,'Scalable Performance, Stability'!B:B,"must_have")+COUNTIFS('Advanced Security Options (DSS '!V:V,$A17,'Advanced Security Options (DSS '!B:B,"must_have") -> 6 | D17: =COUNTIFS('Architecture, Compute & Infrast'!V:V,$A17,'Architecture, Compute & Infrast'!B:B,"nice_to_have")+COUNTIFS('Enterprise-grade Security, Perm'!V:V,$A17,'Enterprise-grade Security, Perm'!B:B,"nice_to_have")+COUNTIFS('Generative AI Acceleration & In'!V:V,$A17,'Generative AI Acceleration & In'!B:B,"nice_to_have")+COUNTIFS('Scalable Performance, Stability'!V:V,$A17,'Scalable Performance, Stability'!B:B,"nice_to_have")+COUNTIFS('Advanced Security Options (DSS '!V:V,$A17,'Advanced Security Options (DSS '!B:B,"nice_to_have") -> 6
A18: Not Applicable | B18: =COUNTIF('Architecture, Compute & Infrast'!V:V,$A18)+COUNTIF('Enterprise-grade Security, Perm'!V:V,$A18)+COUNTIF('Generative AI Acceleration & In'!V:V,$A18)+COUNTIF('Scalable Performance, Stability'!V:V,$A18)+COUNTIF('Advanced Security Options (DSS '!V:V,$A18) -> 11 | C18: =COUNTIFS('Architecture, Compute & Infrast'!V:V,$A18,'Architecture, Compute & Infrast'!B:B,"must_have")+COUNTIFS('Enterprise-grade Security, Perm'!V:V,$A18,'Enterprise-grade Security, Perm'!B:B,"must_have")+COUNTIFS('Generative AI Acceleration & In'!V:V,$A18,'Generative AI Acceleration & In'!B:B,"must_have")+COUNTIFS('Scalable Performance, Stability'!V:V,$A18,'Scalable Performance, Stability'!B:B,"must_have")+COUNTIFS('Advanced Security Options (DSS '!V:V,$A18,'Advanced Security Options (DSS '!B:B,"must_have") -> 6 | D18: =COUNTIFS('Architecture, Compute & Infrast'!V:V,$A18,'Architecture, Compute & Infrast'!B:B,"nice_to_have")+COUNTIFS('Enterprise-grade Security, Perm'!V:V,$A18,'Enterprise-grade Security, Perm'!B:B,"nice_to_have")+COUNTIFS('Generative AI Acceleration & In'!V:V,$A18,'Generative AI Acceleration & In'!B:B,"nice_to_have")+COUNTIFS('Scalable Performance, Stability'!V:V,$A18,'Scalable Performance, Stability'!B:B,"nice_to_have")+COUNTIFS('Advanced Security Options (DSS '!V:V,$A18,'Advanced Security Options (DSS '!B:B,"nice_to_have") -> 5
A19: Total | B19: =SUM(B14:B18) -> 67 | C19: =SUM(C14:C18) -> 38 | D19: =SUM(D14:D18) -> 29
A21: Per-section breakdown
A22: Section | B22: Pass | C22: Fail | D22: Partial | E22: Needs Review | F22: Not Applicable | G22: Total
A23: Architecture, Compute & Infrast | B23: =COUNTIF('Architecture, Compute & Infrast'!V:V,"Pass") -> 5 | C23: =COUNTIF('Architecture, Compute & Infrast'!V:V,"Fail") -> 2 | D23: =COUNTIF('Architecture, Compute & Infrast'!V:V,"Partial") -> 5 | E23: =COUNTIF('Architecture, Compute & Infrast'!V:V,"Needs Review") -> 5 | F23: =COUNTIF('Architecture, Compute & Infrast'!V:V,"Not Applicable") -> 0 | G23: =SUM(B23:F23) -> 17
A24: Enterprise-grade Security, Perm | B24: =COUNTIF('Enterprise-grade Security, Perm'!V:V,"Pass") -> 4 | C24: =COUNTIF('Enterprise-grade Security, Perm'!V:V,"Fail") -> 0 | D24: =COUNTIF('Enterprise-grade Security, Perm'!V:V,"Partial") -> 2 | E24: =COUNTIF('Enterprise-grade Security, Perm'!V:V,"Needs Review") -> 3 | F24: =COUNTIF('Enterprise-grade Security, Perm'!V:V,"Not Applicable") -> 1 | G24: =SUM(B24:F24) -> 10
A25: Generative AI Acceleration & In | B25: =COUNTIF('Generative AI Acceleration & In'!V:V,"Pass") -> 1 | C25: =COUNTIF('Generative AI Acceleration & In'!V:V,"Fail") -> 1 | D25: =COUNTIF('Generative AI Acceleration & In'!V:V,"Partial") -> 0 | E25: =COUNTIF('Generative AI Acceleration & In'!V:V,"Needs Review") -> 1 | F25: =COUNTIF('Generative AI Acceleration & In'!V:V,"Not Applicable") -> 8 | G25: =SUM(B25:F25) -> 11
A26: Scalable Performance, Stability | B26: =COUNTIF('Scalable Performance, Stability'!V:V,"Pass") -> 2 | C26: =COUNTIF('Scalable Performance, Stability'!V:V,"Fail") -> 8 | D26: =COUNTIF('Scalable Performance, Stability'!V:V,"Partial") -> 1 | E26: =COUNTIF('Scalable Performance, Stability'!V:V,"Needs Review") -> 3 | F26: =COUNTIF('Scalable Performance, Stability'!V:V,"Not Applicable") -> 2 | G26: =SUM(B26:F26) -> 16
A27: Advanced Security Options (DSS | B27: =COUNTIF('Advanced Security Options (DSS '!V:V,"Pass") -> 3 | C27: =COUNTIF('Advanced Security Options (DSS '!V:V,"Fail") -> 10 | D27: =COUNTIF('Advanced Security Options (DSS '!V:V,"Partial") -> 0 | E27: =COUNTIF('Advanced Security Options (DSS '!V:V,"Needs Review") -> 0 | F27: =COUNTIF('Advanced Security Options (DSS '!V:V,"Not Applicable") -> 0 | G27: =SUM(B27:F27) -> 13
A29: Critical findings - must-have items that Fail (root cause first)
A30: ID | B30: Section | C30: Title | D30: Status | E30: Key point
A31: SCALE-009 | B31: Scalable Performance, Stability | C31: Flow Limits Sizing (Max Jobs, Max Activities) | D31: Fail | E31: CRITICAL, and the likely root cause of the instability. Max running jobs = 0 means no limit. Each job spawns a 2GB-heap JEK that is not in any cgroup, so concurrent jobs can push the 62GB, no-swap host past physical RAM, on top of the 40G cgroup budget and the 8g backend. That matches the native-memory crash dumps (Mar and Jul 2026). Fix: set maxRunningJobs using the 5-step framework, e.g. 62GB - OS ~4GB - backend 8g ~ 50GB; about 70% to cgroups (~35-40G) leaves ~10-12GB for JEKs, so about 5 concurrent jobs at 2g. Raise maxRunningActivities to 30-50 only as a backstop above Max Jobs; the current value of 5 is well below the recommended band. Also offload recipes to K8s (ARCH-016) to cut host memory pressure. Linked: SEC-004, SCALE-008.
A32: SCALE-001 | B32: Scalable Performance, Stability | C32: External PostgreSQL Runtime Database | D32: Fail | E32: The runtime DB is still the embedded H2, which is not production-grade for a 25-user instance. Migrate to an external PostgreSQL. Set maxPooledExternalConnections to at least 2x Postgres max_connections, and align DB backups with DSS backups (SCALE-005).
A33: ARCH-004 | B33: Architecture, Compute & Infrast | C33: SSD Storage for DSS | D33: Fail | E33: DSS's own sanity check flags rotational storage for DATA_DIR. Caveat: this is a GCP VM (hostname gcp9234prdapp04, metadata.google.internal), and GCP persistent disks always report ROTA=1. Confirm the actual PD type (pd-standard is HDD; pd-balanced/pd-ssd are SSD). If it is pd-standard, migrate /apps to pd-balanced or pd-ssd. With 25 users and heavy logs, disk I/O matters.
A34: SCALE-007 | B34: Scalable Performance, Stability | C34: Backend.log Error Review | D34: Fail | E34: Several systemic, recurring errors: (1) unified-monitoring graphite parsing and RRD writes for API deployments on an old 'PND_Local' infra (stale deployments or monitoring entries; clean up or fix); (2) scenarios whose run-as users (ds10, vgupta11) no longer exist (reassign or disable; see SCALE-004); (3) orphaned code-studio webapp executions calling back (clean up stale K8s code-studio deployments; see ARCH-012). None crashes DSS on its own, but together they flood the logs and hide real problems.
A35: SCALE-004 | B35: Scalable Performance, Stability | C35: Admin Project for Garbage Collection | D35: Fail | E35: An admin project exists but has no garbage-collection scenarios, and its one scheduled scenario is broken (its run-as user was deleted). Add scheduled macros for old job logs/scenario runs, idle Jupyter kernels and temp files per the Setup Maintenance Jobs wiki, and fix the run-as user. Log volume is high: backend/nginx/ipython logs rotate at 100MB.
A36: SCALE-012 | B36: Scalable Performance, Stability | C36: Cloud Object Storage Configuration (Details Readable By, HDFS Interface) | D36: Fail | E36: Spark is enabled and used, but one Azure connection has no details-readable groups (DSS itself warns), and none of the three cloud storage connections has an HDFS interface. Set GS for GCS, and ABFS (if hierarchical namespace is enabled) or WASB for Azure. Grant details-read to the groups that run Spark on these connections.
A37: SCALE-015 | B37: Scalable Performance, Stability | C37: Amazon Redshift, Google BigQuery, Azure Synapse Connection Configuration | D37: Fail | E37: Automatic fast-write is off on both BigQuery connections, so writes go row-by-row through DSS. Enable it, pointing to a GCS connection with compatible auth (the ear21183 GCS connection is a natural pairing for ear21183 BigQuery). No Redshift or Synapse connections exist.
A38: SCALE-011 | B38: Scalable Performance, Stability | C38: Remove filesystem_root Connection | D38: Fail | E38: filesystem_root still exists. Access is limited to admin and data-scientist groups, which reduces the risk but still exposes the whole server filesystem. Check usage in Admin > Monitoring. If used, create a scoped connection to the specific path, migrate, then delete filesystem_root.
A39: ADVSEC-001 | B39: Advanced Security Options (DSS | C39: Hiding error stacks | D39: Fail | E39: Stack traces are shown to logged-in users. Set security.hideErrorStacks=true.
A40: ADVSEC-004 | B40: Advanced Security Options (DSS | C40: Expiring sessions | D40: Fail | E40: Sessions never expire. Set a finite idle timeout and/or maximum duration (e.g. 8-12h max, 60-120 min idle), and warn users about possible loss of unsaved work in Jupyter.
A41: ADVSEC-005 | B41: Advanced Security Options (DSS | C41: Forcing a single session per user | D41: Fail | E41: Multiple concurrent sessions per user are allowed (the default). Enable 'Force single session per user' if it fits how users work.
... A44: GENAI-003 | B44: Generative AI Acceleration & In | C44: Trace Explorer Default Configuration | D44: Fail | E44: The Trace Explorer plugin is installed and LLM Mesh is in heavy use (9 AzureOpenAI connections, cost quotas), but no default project/webapp is set, so 'View traces' shortcuts will not work. Create a Trace Explorer webapp and set it in Admin > Settings > LLM Mesh > Trace.
A46: Other must-have items - Partial or Needs Review
A47: ID | B47: Section | C47: Title | D47: Status | E47: Key point
A48: ARCH-001 | B48: Architecture, Compute & Infrast | C48: Separation of Design and Automation Nodes | D48: Partial | E48: The bundle is from a single design node. The URLs suggest the organisation runs a separate deploy/automation estate, but this node uses its own local deployer and has no project-deployer infrastructure attached to push bundles to an automation node. API services (CPS_2, SFP, iSeeds3) are served from this design node's local STATIC infra. Confirm with the customer where production workloads run, and whether the Design -> Deployer -> Automation path is used.
A49: ARCH-008 | B49: Architecture, Compute & Infrast | C49: Functional Validation of Spark Execution (Recipe & Notebook) | D49: Needs Review | E49: Spark-on-K8s recipes are clearly being submitted, but a static bundle cannot confirm end-to-end success or executor-pod visibility for notebooks. Run the documented test recipe and the Spark notebook test.
A50: ARCH-009 | B50: Architecture, Compute & Infrast | C50: Bidirectional Network Connectivity Between DSS and Elastic AI Cluster | D50: Needs Review | E50: Worker-to-DSS connectivity works at least for job start (pods are created). The port-forward and read-timeout errors on K8s webapps suggest intermittent DSS <-> cluster connectivity issues. Validate both directions with a pySpark recipe using toPandas()/collect(), and check for a HEAD operation in the Main Activity Log.
A51: ARCH-012 | B51: Architecture, Compute & Infrast | C51: Functional Validation of Containerized Execution Across Recipe, Notebook, Webapp, and API | D51: Needs Review | E51: Webapps and code studios run on K8s, but the recurring intercom 'Unknown execution context' errors point to orphaned or stale container executions calling back. API services are deployed to a STATIC infra, not K8s, so the API-on-K8s test has no evidence. Run the four functional tests (recipe, notebook, webapp, API).
A52: ARCH-015 | B52: Architecture, Compute & Infrast | C52: Appropriate Cluster Sizing | D52: Needs Review | E52: Illustrative estimate from Dataiku's formula: Spark recipes about 5 x 2 x 4g x 1.2 = 48GB; Spark notebooks about 8 (30% of 25 users) x 2 x 4g x 1.2 = 77GB; Jupyter about 8 x 4GB (py_small limit) = 32GB. Total about 157GB of cluster memory, plus disk about 25GB x executor instances. Get the GKE node-pool size and utilisation, and any pending-pod or OOMKilled history, before judging sizing.
A53: ARCH-016 | B53: Architecture, Compute & Infrast | C53: Global Default Cluster and Default Execution Config Set (if Elastic AI used) | D53: Partial | E53: The default cluster is set, but no global default container config is set, so recipes and notebooks run locally unless each one is configured. If most workloads are meant to be offloaded (which the heavy K8s webapp/Spark use suggests), set defaultExecutionConfig to a bounded config such as py_small_config or py_medium_config. This also relieves memory pressure on the 62GB host (see SCALE-009).
A54: SEC-003 | B54: Enterprise-grade Security, Perm | C54: UIF-Managed CGroup Hierarchies Allowed Directories | D54: Needs Review | E54: cgroups are active under UIF, so this check applies. Ask the admin for security-config.ini and confirm [dirs] additional_allowed_file_dirs includes /sys/fs/cgroup/memory/DSS.
A55: SEC-004 | B55: Enterprise-grade Security, Perm | C55: CGroups Enabled with Memory Limit per Sizing Heuristic | D55: Partial | E55: The overall limit of 40G is in line with the heuristic (64GB host -> 38g, about 66%). But several process categories have no cgroup placement, which DSS itself warns about. These new categories are often missed after upgrades; add memory/DSS/${user}/... targets for each. Related: SCALE-009, where JEKs are unbounded in number and outside cgroups.
A56: SCALE-005 | B56: Scalable Performance, Stability | C56: Environment Backup Policy | D56: Needs Review | E56: Ask the customer for the backup policy (GCP PD snapshots or file-level backup of DATA_DIR, including the H2 databases until the Postgres migration). Confirm frequency, retention and a tested restore.
A58: Recommendations (priority order; linked issues grouped)
A59: # | B59: Action | C59: Related IDs | E59: Detail
A60: 1 | B60: Stop host memory exhaustion (root cause of recent crashes) | C60: SCALE-009, SEC-004, SEC-005, SCALE-008 | E60: Set Max running jobs (jekSettings.maxRunningJobs) from 0 to a sized value (~5 at 2g JEK on this 62GB, no-swap host). Add cgroup targets for the 6 process types DSS flags. Consider adding swap or more RAM. The Mar-2026 and Jul-2026 native-memory JVM crashes are consistent with unbounded JEKs outside cgroups.
A61: 2 | B61: Offload compute to Kubernetes by default | C61: ARCH-016, ARCH-017, ARCH-006, ARCH-010 | E61: Set a default container exec config and the CDE visual-recipe default, and build the CDE image. Differentiate the 3 identical Spark configs. Rebuild or replace the missing dataiku-exec-gpu:13.4.2 image. This moves load off the DSS host (reinforces #1).
A62: 3 | B62: Migrate runtime DB from H2 to PostgreSQL, and put backups in place | C62: SCALE-001, SCALE-005, SCALE-016 | E62: H2 databases (jobs.mv.db ~107MB) are active. Move them to external Postgres, size the connection pool, and document a backup/restore policy covering DATA_DIR and the DB.
A63: 4 | B63: Clean up systemic log errors and maintenance | C63: SCALE-007, SCALE-004, SCALE-006, ARCH-012 | E63: Reassign or disable scenarios run as deleted users (ds10, vgupta11); remove stale PND_Local API deployment monitoring entries; clean orphaned code-studio webapp executions; add log and idle-kernel GC scenarios to ADMINISTRATIONPROJECT; clear the open sanity-check warnings.
A64: 5 | B64: Storage and data-path performance | C64: ARCH-004, SCALE-012, SCALE-015, SCALE-002 | E64: Confirm the GCP PD type backing /apps (move to pd-balanced/pd-ssd if pd-standard). Set HDFS interfaces (GS/ABFS) and details-readable groups on cloud storage. Enable BigQuery automatic fast-write via GCS. Switch the metastore from HiveServer2 to DSS internal.
A65: 6 | B65: Security hardening quick wins | C65: ADVSEC-001/002/003/004/005/008/009/012, SCALE-011 | E65: hideErrorStacks, hideVersionStrings, secureCookies (after confirming HTTPS-only), session idle/max timeouts, single session, wiki upload allow-list, export restrictions, non-clickable table links, and remove filesystem_root.
A66: 7 | B66: Plan the 15.x upgrade and architecture discussion | C66: ARCH-002, ARCH-001, ARCH-003, GENAI-003 | E66: Schedule the DSS 15 upgrade (1 major behind) and check RHEL 8 support for it. Confirm the Design -> Deployer -> Automation path. Set the Trace Explorer default webapp.

Sheet Architecture, Compute & Infrast
A1: id | B1: priority | C1: check_type | D1: subtopic | E1: title | F1: statement | G1: parameter_hint | H1: operator | I1: expected_value | J1: unit | K1: expected_condition_notes | L1: supporting_evidence | M1: contradicting_evidence | N1: insufficient_evidence_handling | O1: rationale | P1: dataiku_concepts | Q1: source_document | R1: source_page | S1: source_section | T1: confidence | U1: ambiguity_notes | V1: validation_status | W1: evidence_found | X1: notes | Y1: validated_at | Z1: validated_by
A2: ARCH-001 | B2: must_have | C2: qualitative_practice | D2: Deployment Infrastructure | E2: Separation of Design and Automation Nodes | F2: Production-grade Dataiku deployments should separate experimental/design work from production runs by leveraging dedicated automation nodes; reviewers should discuss the Design -> Deployer -> Automation Node architecture with the customer and flag gaps, even though standing up new nodes is out of scope for the review itself. | L2: Diagnosis shows a distinct automation node (or nodes) separate from the design node, with a deployer configured and bundles being pushed from design to automation. | M2: Only a single design node is used to run both experimentation and production workloads, with no automation node or deployer in use. | N2: If the diagnosis file does not expose node topology/roles, flag needs_manual_review and recommend discussing the Design -> Deployer -> Automation architecture directly with the customer. | O2: Mixing experimental and production work on the same node risks instability and is not considered production-ready. | P2: Design node, Automation node, Deployer, Bundles | Q2: architecture_compute_cost | R2: 1, 2 | S2: Dataiku Deployment Infrastructure | MUST HAVE; Dataiku Deployment Infrastructure | MUST HAVE | T2: high | V2: Partial | W2: apps/dss/data_design/install.ini: nodetype=design, nodeid=p4d. apps/dss/data_design/config/general-settings.json deployerClientSettings.mode=LOCAL (a remote nodeUrl https://deploy.ds.p.data.slb.com/ is recorded but not in use); config/project-deployer has only projects/ADMINISTRATIONPROJECT.json and no infrastructures; config/api-deployer/infras/P4D_Local.json type=STATIC, stage=Development. governIntegrationSettings.nodeUrl=https://govern.ds.p.data.slb.com. | X2: The bundle is from a single design node. The URLs suggest the organisation runs a separate deploy/automation estate, but this node uses its own local deployer and has no project-deployer infrastructure attached to push bundles to an automation node. API services (CPS_2, SFP, iSeeds3) are served from this design node's local STATIC infra. Confirm with the customer where production workloads run, and whether the Design -> Deployer -> Automation path is used. | Y2: 2026-09-25 | Z2: Claude (AI-assisted review) - bundle dku_diagnosis_2026-07-22-08-21-05 (node p4d, DSS 14.4.3)
A3: ARCH-002 | B3: nice_to_have | C3: qualitative_practice | D3: Platform Versioning | E3: Regular DSS Version Upgrades | F3: Dataiku recommends customers stay reasonably current on DSS versions to benefit from continuous platform improvements; reviewers should identify and recommend an upgrade if appropriate, but the upgrade itself is a separate service-catalog engagement and should not be performed during the review. | L3: Diagnosis shows a DSS version reasonably close to the latest generally available release. | M3: Diagnosis shows a DSS version many releases behind current, or a version approaching/at end-of-life. | N3: If the diagnosis file lacks version information or there is no context on Dataiku's release cadence, flag needs_manual_review and recommend checking DSS release notes for the customer's version. | O3: Dataiku regularly enriches the platform, so staying current continuously brings value and new opportunities to customers. | P3: DSS version, Upgrade | Q3: architecture_compute_cost | R3: 2 | S3: Dataiku Version | NICE TO HAVE | T3: high | V3: Needs Review | W3: apps/dss/data_design/dss-version.json: product_version=14.4.3 (conf_version 14430). Latest GA found: DSS 15.0.2, released 24 Sep 2026 (15.0.0 released 14 Aug 2026). Source: https://doc.dataiku.com/dss/latest/release_notes/index.html | X3: The bundle is 1 major version behind (14.x vs 15.x). Per the internal rule, a major-version gap means Needs Review, not Fail. Plan a 15.x upgrade as a separate engagement. Remove stale 13.4.2/14.1.4 image references at the same time (see ARCH-010, SCALE-006). | Y3: 2026-09-25 | Z3: Claude (AI-assisted review) - bundle dku_diagnosis_2026-07-22-08-21-05 (node p4d, DSS 14.4.3)
A4: ARCH-003 | B4: must_have | C4: qualitative_practice | D4: Operating System | E4: Supported Operating System Version | F4: DSS should run on an operating system version officially supported by Dataiku, which mainly matters for custom installs since Cloud Stacks provides a supported OS image by default; reviewers should compare the current OS against Dataiku's supported OS list and deprecation notices and recommend upgrades if needed. | L4: Diagnosis or accompanying metadata shows the host OS and version currently listed as supported in Dataiku's Supported Operating Systems documentation. | M4: The host OS/version is deprecated or not on Dataiku's supported list for the installed DSS version. | N4: If the diagnosis file does not capture OS name/version, flag needs_manual_review and cross-check against Dataiku's Supported Operating Systems documentation. | O4: Running on an unsupported OS risks instability and lack of vendor support. | P4: Operating System, Custom install, Cloud Stacks | Q4: architecture_compute_cost | R4: 2 | S4: Operating System Version | MUST HAVE | T4: medium | U4: The source includes an empty 'DiagParser3:' heading with no field specified underneath, so no literal parameter path could be extracted; treated as a qualitative check instead. | V4: Pass | W4: hs_err_pid*.log Host line and diag.txt (/etc/redhat-release): Red Hat Enterprise Linux release 8.10 (Ootpa); kernel 4.18.0-553.144.1.el8_10.x86_64; syspackages.txt: redhat-release-8.10-0.3.el8. | X4: RHEL 8.x is on Dataiku's supported custom-install list for DSS 14 (https://doc.dataiku.com/dss/latest/installation/custom/requirements.html). The page could not be fetched live during this review, so confirm the minor-version floor. Also check that RHEL 8 stays supported for the planned 15.x upgrade (ARCH-002) before scheduling it; RHEL 9 is the longer-lived target. | Y4: 2026-09-25 | Z4: Claude (AI-assisted review) - bundle dku_diagnosis_2026-07-22-08-21-05 (node p4d, DSS 14.4.3)
A5: ARCH-004 | B5: must_have | C5: qualitative_practice | D5: Storage | E5: SSD Storage for DSS | F5: DSS should run on SSD drives rather than legacy rotational hard drives, since rotational disks can significantly degrade performance, especially on larger, multi-user instances (potentially causing a non-workable experience); reviewers should identify currently used disk types and recommend migration to SSD where feasible, noting this is typically easier on cloud than on-premise deployments. | L5: Diagnosis or infrastructure metadata indicates SSD-backed storage underlying the DATADIR. | M5: Diagnosis or infrastructure metadata indicates rotational HDD storage is in use, particularly on a larger or many-user instance. | N5: If the diagnosis file does not report the underlying disk/storage medium, flag needs_manual_review and ask the infrastructure team/customer directly. | O5: Rotational hard drives can severely impact performance and, on larger instances with many users, may lead to a non-workable experience. | P5: Disk I/O, SSD, DATADIR | Q5: architecture_compute_cost | R5: 2, 3 | S5: Use of SSDs | MUST HAVE; Use of SSDs | MUST HAVE | T5: high | V5: Fail | W5: apps/dss/data_design/run/sanity-check.json: WARN_MISC_DISK_ROTATIONAL - DATA_DIR on '/dev/mapper/vg01-vol01' seems to be a rotational hard drive. diag.txt lsblk -t: ROTA=1 for sdb/vg01-vol01 (800G, 74% used, mounted /apps). | X5: DSS's own sanity check flags rotational storage for DATA_DIR. Caveat: this is a GCP VM (hostname gcp9234prdapp04, metadata.google.internal), and GCP persistent disks always report ROTA=1. Confirm the actual PD type (pd-standard is HDD; pd-balanced/pd-ssd are SSD). If it is pd-standard, migrate /apps to pd-balanced or pd-ssd. With 25 users and heavy logs, disk I/O matters. | Y5: 2026-09-25 | Z5: Claude (AI-assisted review) - bundle dku_diagnosis_2026-07-22-08-21-05 (node p4d, DSS 14.4.3)
A6: ARCH-005 | B6: must_have | C6: specific_setting | D6: Spark Configuration | E6: Valid Spark Configuration for Spark Jobs | F6: Environments that run Spark jobs must have a valid Spark configuration set (general-settings.json under sparkSettings, or via Administration > Settings > Spark); the specific example values Dataiku provides are only a baseline, not a strict requirement, but a workable config must exist wherever Spark is used. | G6: general-settings.json > sparkSettings | H6: exists | I6: valid spark configuration present | K6: Required only if the environment executes Spark jobs; the specific parameter values shown by Dataiku are illustrative, not mandatory. | L6: sparkSettings block is present and non-empty in general-settings.json, consistent with evidence of successful Spark job execution elsewhere in the diagnosis. | M6: sparkSettings is missing or empty while the instance shows evidence of Spark recipes/jobs being used. | N6: If the diagnosis file does not indicate whether Spark is used at all, flag needs_manual_review to confirm with the customer whether Spark jobs are run. | O6: Without a valid Spark config, Spark jobs cannot execute at all. | P6: Spark, general-settings.json, sparkSettings | Q6: architecture_compute_cost | R6: 3, 4 | S6: Spark runtime configurations | MUST HAVE if running spark jobs; Spark runtime configurations | MUST HAVE if running spark jobs | T6: high | V6: Pass | W6: apps/dss/data_design/config/general-settings.json sparkSettings.sparkEnabled=true with 3 executionConfigs (spark_small_config/spark_medium_config/spark_large_config), managedKubernetes=true, spark.driver.host=10.196.183.29. backend.log*: 'dku.spark.submit.k8s.helper - Setting up managed Kubernetes context' and 'dku.jobs.postactions.pods - Pods corresponding to job' (Spark on K8s is in use). Spark base images built for 14.4.3 (run/built-base-images.json). | X6: A valid Spark config exists and is being used. Related sanity warning: WARN_CONNECTION_SPARK_NO_GROUP_WITH_DETAILS_READ_ACCESS on 'ear27331_blob_stg_1' (see SCALE-012). The configs are all sized identically (see ARCH-006). | Y6: 2026-09-25 | Z6: Claude (AI-assisted review) - bundle dku_diagnosis_2026-07-22-08-21-05 (node p4d, DSS 14.4.3)
A7: ARCH-006 | B7: nice_to_have | C7: specific_setting | D7: Spark Configuration | E7: Baseline Spark Configuration Set (High/Standard/Large-memory/High I/O) | F7: Dataiku recommends defining multiple named Spark configurations as a tunable baseline: a default Standard config for recipes and notebooks, a High config for higher parallelism, a Large memory config for the largest jobs, and an optional High I/O config for read/write-heavy workloads with a high cores-to-memory ratio. | G7: general-settings.json > sparkSettings (named spark configs) | H7: one_of | I7: Standard/High/Large-memory baseline configs, plus optional High I/O config, as documented | K7: Baseline reference values: Standard config \4, spspark.executor.memory=6g, spark.executor.cores=2, spark.kubernetes.memoryOverheadFactor=0.4, spark.driver.memory=1g, spark.sql.shuffle.partitions=40, spark.sql.broadcastTimeout=3600, spark.port.maxRetries=200, spark.driver.host=<DSS host IP>. High config - spark.executor.instances=12, spark.executor.memory=6g, spark.executor.cores=2, spark.kubernetes.memoryOverheadFactor=0.4, spark.driver.memory=1g, spark.sql.shuffle.partitions=80, spark.sql.broadcastTimeout=3600, spark.port.maxRetries=200, spark.driver.host=<DSS host IP>. Large memory config - spark.executor.instances=4, spark.executor.memory=12g, spark.executor.cores=2, spark.kubernetes.memoryOverheadFactor=0.6, spark.driver.memory=3g, spark.sql.shuffle.partitions=80, spark.sql.broadcastTimeout=3600, spark.port.maxRetries=200, spark.driver.host=<DSS host IP>. Optional High I/O config (only if there is a use case for it) - spark.executor.instances=2, spark.executor.memory=16g, spark.executor.cores=8, spark.kubernetes.memoryOverheadFactor=0.4, spark.driver.memory=3g, spark.sql.shuffle.partitions=40, spark.sql.broadcastTimeout=3600, spark.port.maxRetries=200, spark.driver.host=<DSS host IP>. These values are guidance, not a requirement. | L7: sparkSettings contains multiple named configs roughly matching these purposes (default/high-parallelism/large-memory, and optionally high I/O). | M7: Only a single undifferentiated spark config exists despite varied workload needs (e.g., both lightweight recipes and large jobs run identically). | N7: If the diagnosis file does not list multiple sparkSettings configs or describe workload diversity, flag needs_manual_review and ask about workload variety. | O7: Different Spark workloads (lightweight recipes vs. large jobs vs. I/O-heavy jobs) benefit from different executor sizing and parallelism trade-offs. | P7: Spark executor, Spark configuration, Kubernetes | Q7: architecture_compute_cost | R7: 4, 5 | S7: Define three spark configs - NICE TO HAVE; Special spark configs (only if there's use case for it) | T7: high | V7: Fail | W7: apps/dss/data_design/config/general-settings.json sparkSettings.executionConfigs: spark_small_config, spark_medium_config and spark_large_config all have the same conf: spark.executor.memory=4g, spark.sql.shuffle.partitions=40, spark.kubernetes.memoryOverheadFactor=0.2, spark.kubernetes.executor.limit.cores=1. No spark.executor.instances/cores/driver.memory set. configForJupyter/SEK/Interactive=spark_small_config. | X7: The three named configs suggest intent to tier workloads, but they are functionally identical, so 'medium' and 'large' give no extra capacity. Differentiate them, e.g. medium: executor.instances=12 and shuffle.partitions=80; large: executor.memory=12g, memoryOverheadFactor=0.6, driver.memory=3g. Set explicit executor.instances/cores. Dataiku's baseline values are guidance only. | Y7: 2026-09-25 | Z7: Claude (AI-assisted review) - bundle dku_diagnosis_2026-07-22-08-21-05 (node p4d, DSS 14.4.3)
A8: ARCH-007 | B8: nice_to_have | C8: specific_setting | D8: Spark Configuration | E8: Kubernetes Namespace and Auth Recommendations for Spark | F8: For Spark-on-Kubernetes, Dataiku recommends one Kubernetes namespace per user (e.g. dss-ns-${dssUserLogin}), auto-creating namespaces, ensuring namespace names are Kubernetes-compliant, and dynamically creating service accounts for authentication mode. | G8: general-settings.json > sparkSettings (Kubernetes namespace/authentication settings) | H8: equals | I8: one namespace per user (dss-ns-${dssUserLogin}), auto-create namespaces enabled, K8s-compliant naming, dynamic service account creation | K8: No single literal diag field was given for this sub-setting; pointer is a best-effort conceptual location within sparkSettings/Kubernetes settings. | L8: Namespace naming pattern and auto-create/dynamic service account settings match the recommendation. | M8: A single shared namespace is used for all users, or service accounts are managed manually rather than dynamically. | N8: If the diagnosis file does not expose namespace or authentication configuration for Spark-on-Kubernetes, flag needs_manual_review. | O8: Per-user namespace isolation improves security boundaries and resource tracking on Kubernetes. | P8: Kubernetes namespace, Service account, Spark on Kubernetes | Q8: architecture_compute_cost | R8: 5 | S8: Recommended Settings NICE TO HAVE | T8: medium | V8: Partial | W8: apps/dss/data_design/config/general-settings.json sparkSettings.executionConfigs[*].kubernetesSettings: managedNamespace='${namespace}', authenticationMode=DYNAMIC_SERVICE_ACCOUNT, createNamespace=false, ensureNamespaceCompliance=false. At runtime the namespace resolves per project, not per user: backend.log* shows 'kubectl --namespace dss-29925-p4d' (14,143 occurrences). apps/dss/data_design/config/clusters/P4D.json type=manual. | X8: The per-user namespace shortcut does not apply because this is a manual (externally registered) cluster, so the item was judged on its merits. Dynamic service accounts are used (good). The namespace is templated, but it resolves per project/EAR (dss-<EAR>-p4d) rather than per user. Auto-create and K8s-compliance enforcement are off. This may be a deliberate per-project isolation model; confirm with the customer. If per-user isolation is wanted, use dss-ns-${dssUserLogin}, enable createNamespace and enable ensureNamespaceCompliance. | Y8: 2026-09-25 | Z8: Claude (AI-assisted review) - bundle dku_diagnosis_2026-07-22-08-21-05 (node p4d, DSS 14.4.3)
A9: ARCH-008 | B9: must_have | C9: qualitative_practice | D9: Spark Validation | E9: Functional Validation of Spark Execution (Recipe & Notebook) | F9: Reviewers should functionally validate Spark execution: run a Spark-engine recipe on Kubernetes in a test project (should succeed), and separately launch a Python/R/Scala notebook with starter Spark code and run it locally (should succeed, with Spark executor pods visible in the cluster while the code runs). | L9: Job/notebook execution logs show successful completion of a Spark recipe and a Spark notebook session, and cluster monitoring shows executor pods created during notebook execution. | M9: The Spark recipe or notebook execution fails, hangs, or no executor pods ever appear in the cluster. | N9: If the diagnosis file lacks job/notebook execution logs or cluster pod visibility, flag needs_manual_review and recommend running these test steps manually. | O9: Confirms Spark integration works end-to-end, beyond just having a syntactically valid configuration. | P9: Spark recipe, Spark notebook, Kubernetes executor pods | Q9: architecture_compute_cost | R9: 5, 6, 7 | S9: Additional Spark testing; Spark on Notebook MUST HAVE; Spark on Notebook MUST HAVE | T9: high | V9: Needs Review | W9: backend.log*: 'dku.spark.submit.k8s.helper - Dumping namespace pods state before starting Spark job' (12x) and 'dku.jobs.postactions.pods - Pods corresponding to job' (15x) show Spark jobs launching pods in dss-29925-p4d. No SparkException or failed-job pattern was found. No notebook-side Spark session evidence. | X9: Spark-on-K8s recipes are clearly being submitted, but a static bundle cannot confirm end-to-end success or executor-pod visibility for notebooks. Run the documented test recipe and the Spark notebook test. | Y9: 2026-09-25 | Z9: Claude (AI-assisted review) - bundle dku_diagnosis_2026-07-22-08-21-05 (node p4d, DSS 14.4.3)
A10: ARCH-009 | B10: must_have | C10: qualitative_practice | D10: Network Connectivity | E10: Bidirectional Network Connectivity Between DSS and Elastic AI Cluster | F10: Full bidirectional network connectivity between DSS and the Kubernetes/Elastic AI cluster is mandatory: workers must be able to reach Dataiku (required for Spark to start and for any container execution), and Dataiku must be able to reach workers (required for operations that bring data back to the driver, e.g. toPandas/collect/head/show/broadcast join). This should be validated by running a pySpark recipe that pulls data back to the driver and confirming success via the Main Activity Log. | L10: A pySpark recipe using collect/head/show/toPandas completes successfully, with a corresponding HEAD operation visible in the Main Activity Log, and no worker-to-DSS or DSS-to-worker connectivity errors appear in logs. | M10: Connection timeouts or errors between workers and the DSS host in logs, or driver-return operations failing/hanging. | N10: If the diagnosis file lacks job logs or network topology details, flag needs_manual_review and recommend running the described test recipe. | O10: Both directions of connectivity are mandatory prerequisites for Spark to start and for common data-return operations to work. | P10: Spark driver, Spark workers, Network connectivity, Kubernetes | Q10: architecture_compute_cost | R10: 7 | S10: Connectivity between Dataiku and Elastic AI must be fully open MUST HAVE | T10: high | V10: Needs Review | W10: spark.driver.host=10.196.183.29 is set in every Spark config. backend.log*: 26x java.net.SocketTimeoutException 'Read timed out' and 30x 'Could not stop Kubernetes deployment' [dku.webapps.kubernetes]; several kubectl port-forward 'error forwarding port' / 'connect() failed (Connection refused)' lines. | X10: Worker-to-DSS connectivity works at least for job start (pods are created). The port-forward and read-timeout errors on K8s webapps suggest intermittent DSS <-> cluster connectivity issues. Validate both directions with a pySpark recipe using toPandas()/collect(), and check for a HEAD operation in the Main Activity Log. | Y10: 2026-09-25 | Z10: Claude (AI-assisted review) - bundle dku_diagnosis_2026-07-22-08-21-05 (node p4d, DSS 14.4.3)
A11: ARCH-010 | B11: must_have | C11: specific_setting | D11: Containerized Execution | E11: Valid Containerized Execution Configuration | F11: Environments using Elastic Compute (Kubernetes) must have at least one valid containerized execution configuration set up (general-settings.json > containerSettings, or Administration > Settings > Containerized execution); as with Spark, the specific example values are only a baseline, not a strict requirement. | G11: general-settings.json > containerSettings | H11: exists | I11: valid containerized execution configuration present | K11: Required only when the customer uses Elastic Compute/Kubernetes for offloaded workloads. | L11: containerSettings block is present with at least one named config with reasonable memory requests/limits. | M11: containerSettings is missing or empty while the instance shows evidence of Kubernetes-based execution elsewhere in the diagnosis. | N11: If the diagnosis file does not clarify whether Elastic Compute is used, flag needs_manual_review. | O11: A valid container exec config is required to run workloads in Kubernetes. | P11: Containerized execution, containerSettings, Elastic Compute | Q11: architecture_compute_cost | R11: 8 | S11: Containerized execution configs | MUST HAVE if using Elastic Compute | T11: high | V11: Pass | W11: apps/dss/data_design/config/general-settings.json containerSettings.executionConfigs: 5 KUBERNETES configs. py_small_config 1024/4096MB, py_medium_config 6144/12288MB, py_large_config 8192/16384MB, py_gpu_medium_config 6144/12288MB + 1 GPU, py_gpu_large_config 8192/16384MB + GPU. All have memory/CPU requests and limits. defaultK8sClusterId='P4D'. | X11: A K8s cluster is attached (P4D), so this is a must-have and it is met. Gap: both GPU configs use baseImage 'dataiku-exec-gpu:13.4.2', which the sanity check reports as missing (apps/dss/data_design/run/sanity-check.json WARN_MISC_BASE_IMAGE_NOT_FOUND). GPU workloads will fail until a 14.4.3 GPU image is built and referenced. | Y11: 2026-09-25 | Z11: Claude (AI-assisted review) - bundle dku_diagnosis_2026-07-22-08-21-05 (node p4d, DSS 14.4.3)
A12: ARCH-011 | B12: nice_to_have | C12: specific_setting | D12: Containerized Execution | E12: Baseline Container Execution Configs (Standard, Webapp) and Namespace Settings | F12: Dataiku recommends at least two named containerized execution configs as a baseline - a Standard config for notebooks/recipes/ML (memory request 200MB, memory limit 16000MB) and a Webapp config for webapps (memory request 500MB, memory limit 500MB) - plus per-user Kubernetes namespaces (dss-ns-${dssUserLogin}) with K8s-compliant naming and auto-creation, and using the Webapp config for virtual webapp backends run in containers. | G12: general-settings.json > containerSettings (named container exec configs) | H12: one_of | I12: Standard config (memory request 200MB / limit 16000MB) and Webapp config (memory request 500MB / limit 500MB) | J12: MB | K12: Additional recommended settings: one Kubernetes namespace per user (dss-ns-${dssUserLogin}), K8s-compliant namespace names, auto-create namespaces, and virtual webapps configured to run in a container using the Webapp config. | L12: containerSettings includes configs resembling the Standard and Webapp purposes with comparable memory request/limit values, and namespace settings follow a per-user pattern. | M12: A single undifferentiated container config is used for both interactive workloads and webapps, or all users share one namespace. | N12: If the diagnosis file does not list named container configs or namespace settings, flag needs_manual_review. | O12: Separating configs by workload type avoids over- or under-provisioning; per-user namespaces aid isolation and cost tracking. | P12: Containerized execution, Kubernetes namespace, Webapp backend | Q12: architecture_compute_cost | R12: 8, 9 | S12: Recommendations NICE TO HAVE; Recommended Settings | T12: high | V12: Pass | W12: apps/dss/data_design/config/general-settings.json containerSettings: several configs with genuinely different sizes (requests/limits 1G/4G, 6G/12G, 8G/16G, plus GPU variants). virtualWebAppBackendSettings.infra.containerSelection = EXPLICIT_CONTAINER py_small_config. kubernetesNamespace='${namespace}' on all configs (resolves to dss-29925-p4d at runtime). | X12: Pass under the internal calibration: more than one container config with varying sizes is sufficient, even though names and figures differ from the Standard/Webapp example. Notes: (1) virtual webapps run in py_small_config (1G/4G); a dedicated small webapp config would be cleaner. (2) Namespaces resolve per project, not per user (see ARCH-007), and createNamespace/ensureNamespaceCompliance are false. | Y12: 2026-09-25 | Z12: Claude (AI-assisted review) - bundle dku_diagnosis_2026-07-22-08-21-05 (node p4d, DSS 14.4.3)
A13: ARCH-012 | B13: must_have | C13: qualitative_practice | D13: Containerized Execution Validation | E13: Functional Validation of Containerized Execution Across Recipe, Notebook, Webapp, and API | F13: Reviewers should validate containerized execution end-to-end: execute a recipe in Kubernetes, launch a notebook in the cluster (pod visible in Cluster Monitoring UI), create a test webapp configured with a container backend (deployment visible in Cluster Monitoring UI), and deploy an API service to Kubernetes via the API Deployer (deployment visible in Cluster Monitoring UI and callable via sample code). | L13: Cluster monitoring evidence or reviewer test logs show successful recipe execution, a notebook pod, a webapp deployment, and an API deployment all running in Kubernetes, with the API additionally callable via sample code. | M13: Any of the four (recipe, notebook, webapp, API) fails to launch, or no corresponding pods/deployments ever appear in Cluster Monitoring. | N13: If the diagnosis file does not include cluster monitoring or job execution evidence for these workload types, flag needs_manual_review and recommend running these four test steps manually. | O13: Confirms containerized execution actually works for all major workload types, not merely that configuration exists. | P13: Kubernetes, Recipe, Notebook, Webapp, API Deployer, Cluster Monitoring | Q13: architecture_compute_cost | R13: 9, 10, 11, 12 | S13: Additional container execution testing; Webapp MUST HAVE; API MUST HAVE; API MUST HAVE | T13: high | V13: Needs Review | W13: backend.log*: many streamlit/code-studio K8s deployments (e.g. 'kubectl --namespace dss-29925-p4d get deployments -l dataiku.com/dku-execution-id=streamlit-...'), 7,857 'Getting webapp log tail'. 6,840x ERROR '/dip/api/tintercom/containers/get-execution' failed: 'Unknown execution context: code-studio-as-webapp-...'. api-deployer infra P4D_Local type=STATIC (not K8s). | X13: Webapps and code studios run on K8s, but the recurring intercom 'Unknown execution context' errors point to orphaned or stale container executions calling back. API services are deployed to a STATIC infra, not K8s, so the API-on-K8s test has no evidence. Run the four functional tests (recipe, notebook, webapp, API). | Y13: 2026-09-25 | Z13: Claude (AI-assisted review) - bundle dku_diagnosis_2026-07-22-08-21-05 (node p4d, DSS 14.4.3)
A14: ARCH-013 | B14: must_have | C14: specific_setting | D14: Cluster Configuration | E14: Valid Cluster Configuration for Elastic Compute | F14: Environments using Elastic Compute must have at least one valid cluster configured (found under {DATADIR}/config/clusters or Administration > Clusters); Dataiku does not mandate the specific example configuration, only that a workable cluster exists. | G14: {DATADIR}/config/clusters | H14: exists | I14: at least one valid cluster configuration present | L14: The clusters config/directory contains at least one properly defined cluster, consistent with other evidence of elastic-compute usage (spark/container jobs running on Kubernetes). | M14: No cluster configuration is present despite evidence of Kubernetes-based workloads elsewhere in the diagnosis. | N14: If the diagnosis file does not clarify whether Elastic Compute is used at all, flag needs_manual_review. | O14: A valid cluster is required to offload computation to Kubernetes. | P14: Cluster, Managed cluster, Unmanaged cluster, Elastic AI | Q14: architecture_compute_cost | R14: 12, 13 | S14: Cluster configurations | MUST HAVE if using Elastic Compute; Cluster configurations | MUST HAVE if using Elastic Compute | T14: high | V14: Pass | W14: apps/dss/data_design/config/clusters/P4D.json: name=P4D, architecture=KUBERNETES, type=manual, permissions granted to 9 groups. apps/dss/data_design/config/general-settings.json defaultK8sClusterId='P4D'. | X14: A valid K8s cluster definition exists and is the global default. It is a manual (externally managed) cluster; see ARCH-014 for topology. | Y14: 2026-09-25 | Z14: Claude (AI-assisted review) - bundle dku_diagnosis_2026-07-22-08-21-05 (node p4d, DSS 14.4.3)
A15: ARCH-014 | B15: nice_to_have | C15: specific_setting | D15: Cluster Configuration | E15: Recommended Cluster Topology (Single Managed Cluster, Node Groups, Autoscaling) | F15: Dataiku recommends a single managed cluster with one CPU node group serving containerized execution, ML, Spark, webapp, and API workloads, adding a separate GPU node group only if needed, and enabling a metrics server plus cluster autoscaling. | G15: {DATADIR}/config/clusters (cluster topology / node group / autoscaling settings) | H15: equals | I15: single managed cluster, one CPU node group for all standard workloads, optional GPU node group only if needed, metrics server installed, autoscaling enabled | K15: No literal single field was given for this recommendation; pointer is a best-effort conceptual location within the clusters config. | L15: Cluster configuration shows one managed cluster with a shared CPU node group, autoscaling enabled, metrics server installed, and a GPU node group only present when GPU workloads exist. | M15: Multiple redundant clusters/node groups without clear justification, no autoscaling enabled, or a GPU node group present without any GPU workload evidence. | N15: If the diagnosis file does not detail node groups or autoscaling settings, flag needs_manual_review. | O15: Simplifies management and reduces cost while retaining elasticity for varying workloads. | P15: Managed cluster, Node group, Autoscaling, Metrics server | Q15: architecture_compute_cost | R15: 14 | S15: Recommended settings NICE TO HAVE | T15: medium | V15: Partial | W15: apps/dss/data_design/config/clusters/P4D.json: single cluster, type=manual, params={} (no node-group, autoscaling or metrics-server details are visible to DSS). | X15: One cluster is used (aligned). It is manually registered, not a DSS-managed cluster, so node groups, autoscaling and metrics server cannot be verified from the bundle. GPU configs exist while the GPU image is missing. Confirm the GKE node pools (CPU plus an optional GPU pool), cluster autoscaler and metrics-server with the infra team. | Y15: 2026-09-25 | Z15: Claude (AI-assisted review) - bundle dku_diagnosis_2026-07-22-08-21-05 (node p4d, DSS 14.4.3)
A16: ARCH-015 | B16: must_have | C16: specific_setting | D16: Cluster Sizing | E16: Appropriate Cluster Sizing | F16: The Kubernetes cluster must be sized appropriately for the customer's workloads - large enough to avoid resource exhaustion but not so large as to waste resources. Dataiku's memory/disk calculation is only an illustrative baseline (not a mandatory formula), derived from Spark settings (general-settings.json > sparkSettings), container exec settings (general-settings.json > containerSettings), and global flow concurrency (general-settings.json > maxRunningActivities). | G16: general-settings.json > sparkSettings, general-settings.json > containerSettings, general-settings.json > maxRunningActivities (used to estimate cluster memory/disk sizing) | H16: greater_than_or_equal | I16: cluster capacity >= estimated total_memory and disk needs derived from the formulas in notes | J16: GB | K16: Illustrative sizing formulas provided by Dataiku, reproduced in full: spark_recipes_memory = global flow concurrency*spark.executor.instances*spark.executor.memory*(1+spark.kubernetes.memoryOverheadFactor) [based on the largest spark config]. spark_notebooks_memory = 30%_DSS_users*spark.executor.instances*spark.executor.memory*(1+spark.kubernetes.memoryOverheadFactor) [using associated spark config]. jupyter_notebooks_memory = 30%_DSS_users * container exec memory limit [using associated container exec config]. total_memory = spark_recipes_memory + spark_notebooks_memory + jupyter_notebooks_memory. DISK = 25GB * spark.executor.instances. Recommended instance sizing: 64 GB < worker size < 128 GB. These are baselines/examples; the cluster need not match this exact calculation, but must be appropriately sized for the customer's workloads based on evidence, and should not be resized without evidence of resource exhaustion. | L16: Cluster memory/CPU capacity is consistent with or exceeds the estimated total_memory/disk needs given current spark/container/concurrency settings, with no signs of chronic resource exhaustion (OOM kills, pending pods) or gross over-provisioning. | M16: Cluster capacity is far below estimated needs (frequent OOM kills/evictions) or drastically oversized relative to workload with no growth justification. | N16: If the diagnosis file lacks cluster capacity metrics or the underlying spark/container/concurrency settings needed to compute the estimate, flag needs_manual_review and recommend gathering these values. | O16: Prevents both instability/performance degradation from under-sizing and cost waste from over-sizing. | P16: Cluster sizing, Spark executor memory, Container exec memory limit, maxRunningActivities, Global flow concurrency | Q16: architecture_compute_cost | R16: 14, 15 | S16: Cluster sizing | MUST HAVE; Cluster sizing | MUST HAVE | T16: high | V16: Needs Review | W16: No cluster capacity metrics in the bundle. Inputs: apps/dss/data_design/config/general-settings.json maxRunningActivities=5; Spark configs 4g executor, overhead 0.2, executor.instances unset (default 2); container limits up to 16384MB; 25 enabled users (config/users.json). | X16: Illustrative estimate from Dataiku's formula: Spark recipes about 5 x 2 x 4g x 1.2 = 48GB; Spark notebooks about 8 (30% of 25 users) x 2 x 4g x 1.2 = 77GB; Jupyter about 8 x 4GB (py_small limit) = 32GB. Total about 157GB of cluster memory, plus disk about 25GB x executor instances. Get the GKE node-pool size and utilisation, and any pending-pod or OOMKilled history, before judging sizing. | Y16: 2026-09-25 | Z16: Claude (AI-assisted review) - bundle dku_diagnosis_2026-07-22-08-21-05 (node p4d, DSS 14.4.3)
A17: ARCH-016 | B17: must_have | C17: specific_setting | D17: Default Compute Settings | E17: Global Default Cluster and Default Execution Config Set (if Elastic AI used) | F17: If the customer intends to offload most or all recipes to Kubernetes, a default cluster (general-settings.json > defaultK8sClusterId) and a default containerized execution config (general-settings.json > defaultExecutionConfig) should be set globally rather than configured per-recipe or per-project; if this global default is set, the associated execution config must have properly configured resource requests/limits rather than being a resource-hogging default. | G17: general-settings.json > defaultK8sClusterId and general-settings.json > defaultExecutionConfig | H17: exists | I17: both set to valid, non-resource-hogging values when Elastic AI/offloading is used broadly | L17: Both defaultK8sClusterId and defaultExecutionConfig are set to valid values, and the referenced execution config has reasonable memory/CPU requests and limits. | M17: These fields are unset despite most recipes being offloaded to Kubernetes, or the default execution config lacks resource limits/requests (resource-hogging risk). | N17: If the diagnosis file does not clarify the proportion of recipes offloaded to Kubernetes, flag needs_manual_review to confirm intended usage pattern with the customer. | O17: Setting a global default simplifies configuration management and avoids inconsistent per-recipe settings; an unset or misconfigured default risks uncontrolled resource usage. | P17: defaultK8sClusterId, defaultExecutionConfig, Containerized execution, Elastic AI | Q17: architecture_compute_cost | R17: 15, 16 | S17: Default Cluster & Default Containerized Execution Config | MUST HAVE if Elastic AI is used; Default Cluster & Default Containerized Execution Config | MUST HAVE if Elastic AI is used | T17: high | V17: Partial | W17: apps/dss/data_design/config/general-settings.json defaultK8sClusterId='P4D' (set); containerSettings.defaultExecutionConfig='' (empty). | X17: The default cluster is set, but no global default container config is set, so recipes and notebooks run locally unless each one is configured. If most workloads are meant to be offloaded (which the heavy K8s webapp/Spark use suggests), set defaultExecutionConfig to a bounded config such as py_small_config or py_medium_config. This also relieves memory pressure on the 62GB host (see SCALE-009). | Y17: 2026-09-25 | Z17: Claude (AI-assisted review) - bundle dku_diagnosis_2026-07-22-08-21-05 (node p4d, DSS 14.4.3)
A18: ARCH-017 | B18: nice_to_have | C18: specific_setting | D18: Containerized Visual Recipes | E18: Containerized Visual Recipes (CDE) Enabled and Base Image Built | F18: If the customer intends to offload visual recipes to Kubernetes, CDE should be enabled (general-settings.json > cdeEnabled) and its base image built via Administration > Settings > Containerized Execution > Build image for containerized visual recipes; a default execution config for visual recipe workloads (general-settings.json > defaultExecutionConfigForVisualRecipesWorkloads) should also be set, validated by confirming a simple recipe (e.g. a sync recipe) shows Engine: DSS (containerized). | G18: general-settings.json > cdeEnabled and general-settings.json > defaultExecutionConfigForVisualRecipesWorkloads | H18: equals | I18: cdeEnabled=true and defaultExecutionConfigForVisualRecipesWorkloads set to a valid execution config | L18: cdeEnabled is true, base CDE image build evidence exists, defaultExecutionConfigForVisualRecipesWorkloads is set, and a sample visual recipe shows Engine: DSS (containerized). | M18: cdeEnabled is false or unset while the customer relies on Kubernetes offloading for visual recipes, or a visual recipe fails to show the containerized engine. | N18: If the diagnosis file does not indicate whether visual recipe offloading to Kubernetes is desired, flag needs_manual_review. | O18: Ensures visual recipes can actually be executed on the cluster with an appropriate base image and default resource config. | P18: CDE, cdeEnabled, Visual recipes, Containerized execution | Q18: architecture_compute_cost | R18: 16, 17, 18 | S18: Containerized Visual Recipes (CDE) | NICE TO HAVE; Containerized Visual Recipes (CDE) | NICE TO HAVE; Containerized Visual Recipes (CDE) | NICE TO HAVE | T18: high | V18: Partial | W18: apps/dss/data_design/config/general-settings.json containerSettings.cdeEnabled=true, cdePluginSupport=true; defaultExecutionConfigForVisualRecipesWorkloads='' (empty). apps/dss/data_design/run/cde-images.json = {} (no CDE image recorded). | X18: CDE is switched on, but no visual-recipe default config is set and no CDE image build is recorded, so visual recipes cannot actually run containerised. Build the CDE image (Admin > Settings > Containerized Execution), set defaultExecutionConfigForVisualRecipesWorkloads, and check that a Sync recipe shows 'Engine: DSS (containerized)'. If visual-recipe offload is not wanted, switch cdeEnabled off to avoid confusion. | Y18: 2026-09-25 | Z18: Claude (AI-assisted review) - bundle dku_diagnosis_2026-07-22-08-21-05 (node p4d, DSS 14.4.3)

Sheet Enterprise-grade Security, Perm
A1: id | B1: priority | C1: check_type | D1: subtopic | E1: title | F1: statement | G1: parameter_hint | H1: operator | I1: expected_value | J1: unit | K1: expected_condition_notes | L1: supporting_evidence | M1: contradicting_evidence | N1: insufficient_evidence_handling | O1: rationale | P1: dataiku_concepts | Q1: source_document | R1: source_page | S1: source_section | T1: confidence | U1: ambiguity_notes | V1: validation_status | W1: evidence_found | X1: notes | Y1: validated_at | Z1: validated_by
A2: SEC-001 | B2: nice_to_have | C2: qualitative_practice | D2: Instance Identification | E2: Verify/Capture Instance IDs | F2: For an established platform, confirm that each node's instance ID (found in {DATA_DIR}/install.ini) is accurately recorded in the platform's tracking/tooling system. | L2: Platform tooling/documentation shows an instance ID for each node matching the value found in {DATA_DIR}/install.ini on that node. | M2: Instance IDs are missing, blank, or mismatched between install.ini and the platform tooling records. | N2: A diagnosis file alone can show the instance ID value in install.ini but cannot confirm whether it is accurately recorded in external platform tooling; flag as needs_manual_review to cross-check against the tooling record. | O2: Accurate instance ID records ensure the platform tooling correctly tracks and manages each node. | P2: install.ini, instance tracking | Q2: security_permissions_compliance | R2: 1, 2 | S2: Verify/Capture Instance IDs | NICE TO HAVE; DiagParser3 | T2: medium | U2: No literal JSON field/diag pointer given beyond the file path itself; this is more a documentation-accuracy check than a technical setting. | V2: Needs Review | W2: apps/dss/data_design/install.ini [general]: installid=GbpIpatzv3MFrFfE6MwSlXCg, nodeid=p4d, nodetype=design. | X2: The instance ID is present and was captured above. Cross-check it against the platform tooling / CMDB record for this node. | Y2: 2026-09-25 | Z2: Claude (AI-assisted review) - bundle dku_diagnosis_2026-07-22-08-21-05 (node p4d, DSS 14.4.3)
A3: SEC-002 | B3: must_have | C3: specific_setting | D3: User Isolation Framework | E3: User Isolation Framework (UIF) Enabled with Appropriate Impersonation Rules | F3: Ensure the User Isolation Framework (UIF) is installed and enabled, with impersonation active and sensible impersonation rules in place (a one-to-one mapping or regex pattern ensuring all DSS users map to identities other than the dataiku service account). For Kubernetes workloads, one namespace per user is recommended; for Hadoop workloads, Sentry/Ranger should be used to manage access. Also check for any Sanity Check warnings regarding UIF. | G3: {DATA_DIR}/config/general-settings.json > impersonation.enabled | H3: equals | I3: true | L3: general-settings.json shows impersonation.enabled: true with userRules configured as a one-to-one mapping or regex rule mapping DSS users to non-service-account identities; no Sanity Check warnings about UIF; for K8s workloads a per-user namespace strategy is evident; for Hadoop workloads Sentry/Ranger integration is present. | M3: impersonation.enabled is false or absent, userRules are missing/overly permissive (e.g., mapping to the dataiku service account), Sanity Check warnings reference UIF, or Kubernetes/Hadoop workloads lack namespace-per-user/Sentry-Ranger controls. | N3: If the diagnosis file lacks general-settings.json impersonation details or workload-specific config, flag as needs_manual_review, noting that longstanding instances without UIF require careful, considerate customer messaging and that disabling/downgrading UIF is not supported. | O3: UIF and correct impersonation rules are required for proper user isolation and security; without them workloads may run under a shared service account, creating security risk and instability in multi-user environments. | P3: User Isolation Framework, impersonation, Kubernetes namespaces, Hadoop Sentry/Ranger | Q3: security_permissions_compliance | R3: 2, 3 | S3: User Isolation Framework | MUST HAVE; User Isolation Framework | MUST HAVE (Front End/Back End/Notes) | T3: high | V3: Pass | W3: apps/dss/data_design/config/general-settings.json impersonation.enabled=true; userRules=[{scope: GLOBAL, type: IDENTITY}]; groupRules=[{type: IDENTITY}]. apps/dss/data_design/install.ini [mus] exec_wrapper_location=/etc/dataiku-security/GbpIpatzv3MFrFfE6MwSlXCg/execwrapper.sh. No UIF-related warnings in apps/dss/data_design/run/sanity-check.json. | X3: UIF is installed and enabled. The IDENTITY rule maps each DSS login to a same-named Unix user, not the service account (dss20677p4ddde01). K8s namespaces are per project, not per user (see ARCH-007). No Hadoop is in use, so Sentry/Ranger does not apply. | Y3: 2026-09-25 | Z3: Claude (AI-assisted review) - bundle dku_diagnosis_2026-07-22-08-21-05 (node p4d, DSS 14.4.3)
A4: SEC-003 | B4: must_have | C4: specific_setting | D4: User Isolation Framework | E4: UIF-Managed CGroup Hierarchies Allowed Directories | F4: Where cgroups are configured under UIF, verify that the cgroup hierarchies controlled by DSS are added to the additional_allowed_file_dirs configuration key under the dirs section of /etc/dataiku-security/INSTALL_ID/security-config.ini. | G4: /etc/dataiku-security/INSTALL_ID/security-config.ini > [dirs] > additional_allowed_file_dirs | H4: exists | I4: DSS-controlled cgroup hierarchy paths listed | K4: Literal file path and key given in source; exact expected paths are environment-specific so only existence/inclusion can be checked. | L4: security-config.ini shows additional_allowed_file_dirs under [dirs] populated with the cgroup hierarchy paths under DSS control. | M4: additional_allowed_file_dirs is missing or does not include the relevant cgroup hierarchy paths despite cgroups being enabled under UIF. | N4: If security-config.ini is not present in the diagnosis bundle, flag as needs_manual_review since this file is typically outside standard diagnostic exports. | O4: Proper directory allowlisting ensures DSS-managed cgroup hierarchies function correctly under user isolation. | P4: cgroups, security-config.ini, User Isolation Framework | Q4: security_permissions_compliance | R4: 3 | S4: User Isolation Framework | MUST HAVE (Back End) | T4: medium | V4: Needs Review | W4: /etc/dataiku-security/GbpIpatzv3MFrFfE6MwSlXCg/security-config.ini is not in the bundle (the etc/ folder only has security/limits.conf). apps/dss/data_design/config/general-settings.json cgroupSettings.enabled=true, cgroupsVersion=CGROUPS_V1, hierarchiesMountPoint=/sys/fs/cgroup, templates under memory/DSS/${user}/... | X4: cgroups are active under UIF, so this check applies. Ask the admin for security-config.ini and confirm [dirs] additional_allowed_file_dirs includes /sys/fs/cgroup/memory/DSS. | Y4: 2026-09-25 | Z4: Claude (AI-assisted review) - bundle dku_diagnosis_2026-07-22-08-21-05 (node p4d, DSS 14.4.3)
A5: SEC-004 | B5: must_have | C5: specific_setting | D5: CGroups | E5: CGroups Enabled with Memory Limit per Sizing Heuristic | F5: Ensure cgroups support is enabled and a memory limit is configured for all memory cgroups, sized according to the recommended heuristic (e.g., 32GB VM -> 10g, 64GB -> 38g, 96GB -> 60g, 128GB+ -> 75% of physical memory), with cgroup placements set for all categories. | G5: {DATA_DIR}/config/general-settings.json > cgroupSettings.enabled | H5: equals | I5: true | K5: Additional checks required: cgroupSettings > cgroups memory limit target should be set and sized per the documented heuristic (approx. 50-75% of physical memory depending on total RAM); no single literal field given for the limit value itself, so compare against the formula in evaluation_guidance. | L5: general-settings.json shows cgroupSettings.enabled: true, targets set for each category under cgroups, and a memory limit configured on memory cgroups (e.g., memory/DSS) that approximates the documented formula based on total instance memory (e.g., ~75% for >120GB, ~66% for 60-120GB, total-20GB for 30-60GB, ~50% below 30GB). Front-end equivalent: Administration > Settings > Resource Control > cgroups shows 'Enable cgroups support' selected with placements and memory limits configured. | M5: cgroupSettings.enabled is false/absent, no memory limit is set on memory cgroups, or the configured limit is far below the heuristic (e.g., unlimited or near-total memory), risking instability. | N5: If cgroupSettings or category placements are not visible in the diagnosis file, flag as needs_manual_review; also check whether the instance was recently reprovisioned (Cloud Stacks) or upgraded, as cgroup limits/placements may not auto-update and new placements may need to be added post-upgrade. | O5: A memory cgroup limit prevents runaway processes from destabilizing or degrading the DSS instance; sizing per the heuristic balances safety with usable memory. | P5: cgroups, memory limits, Resource Control | Q5: security_permissions_compliance | R5: 3, 4, 5 | S5: CGroups | MUST HAVE; CGroups | MUST HAVE (Review steps); CGroups | MUST HAVE (Notes) | T5: high | V5: Partial | W5: apps/dss/data_design/config/general-settings.json cgroupSettings.enabled=true; cgroups: memory/DSS memory.limit_in_bytes=40G, memory/DSS/${user}=6G. Host RAM about 62-64GB (diag.txt free -m total 63885MB; hs_err Host '62G'). Targets are empty for: deploymentHooks, devLambdaServer, customPythonDataAccessComponents, projectStandards, storiesJobs, edaRecipes. apps/dss/data_design/run/sanity-check.json: 5x WARN_SECURITY_PROCESS_TYPE_WITHOUT_MEMORY_LIMIT (In-memory statistics recipes, Custom Python data access components, Project standards, Deployment hooks, Dev lambda server, Stories jobs). | X5: The overall limit of 40G is in line with the heuristic (64GB host -> 38g, about 66%). But several process categories have no cgroup placement, which DSS itself warns about. These new categories are often missed after upgrades; add memory/DSS/${user}/... targets for each. Related: SCALE-009, where JEKs are unbounded in number and outside cgroups. | Y5: 2026-09-25 | Z5: Claude (AI-assisted review) - bundle dku_diagnosis_2026-07-22-08-21-05 (node p4d, DSS 14.4.3)
A6: SEC-005 | B6: must_have | C6: specific_setting | D6: CGroups | E6: JEK-Specific CGroup Limits Left Unconfigured | F6: Do not set specific cgroup limits for individual Job Execution Kernels (JEKs) unless dealing with a rare, highly specialized edge case, as this can cause unexpected execution throttles; JEK-specific cgroups should generally remain unconfigured. | G6: general-settings.json > cgroupSettings (JEK-specific cgroup entries) | H6: not_exists | I6: No JEK-specific cgroup limits configured | K6: No literal field path given for JEK-specific cgroup entries; conceptual pointer based on general cgroupSettings structure. | L6: cgroupSettings configuration shows no per-JEK-specific memory/CPU limits distinct from the general DSS cgroup limits. | M6: Specific cgroup limits are found configured for individual Job Kernels without documented justification for a specialized edge case. | N6: If the diagnosis file does not clearly break down cgroup settings by JEK vs. general placement, flag as needs_manual_review and recommend checking internal deep-dive documentation if an exception is suspected. | O6: Per-JEK cgroup limits can cause unexpected execution throttling, degrading job performance. | P6: cgroups, Job Execution Kernel (JEK) | Q6: security_permissions_compliance | R6: 4 | S6: CGroups | MUST HAVE | T6: medium | U6: Priority classification is inferred; this could arguably be nice_to_have as it's a caution rather than a baseline requirement, but the explicit performance-degradation risk supports must_have. | V6: Pass | W6: apps/dss/data_design/config/general-settings.json cgroupSettings.jobExecutionKernels.targets=[] (no JEK-specific cgroup). | X6: No per-JEK cgroup limits are set, as recommended. JEK memory is therefore controlled only by JEK Xmx and job concurrency, which makes SCALE-009 (maxRunningJobs=0) more serious. | Y6: 2026-09-25 | Z6: Claude (AI-assisted review) - bundle dku_diagnosis_2026-07-22-08-21-05 (node p4d, DSS 14.4.3)
A7: SEC-006 | B7: nice_to_have | C7: specific_setting | D7: HTTPS Configuration | E7: HTTPS Access Configured for DSS | F7: Verify with the customer whether HTTPS access to DSS is configured, either natively via DSS configuration or through a reverse proxy. For custom installations, inspect the [server] section of install.ini; for Cloud Stacks (Fleet Manager) installations, inspect nodes-directory.json in the Instance Diag. | G7: install.ini > [server] section (HTTPS settings) or /data/dataiku/dss_data/run/nodes-directory.json | H7: exists | I7: HTTPS enabled (natively or via reverse proxy) | K7: No single literal key name given for the HTTPS flag itself; pointer is to the file/section where it should be inspected. | L7: install.ini [server] section shows native HTTPS parameters configured, or nodes-directory.json shows HTTPS URLs/ports for nodes, or customer confirms a reverse proxy terminates HTTPS in front of DSS. | M7: Only HTTP is configured with no reverse proxy in front, and install.ini/nodes-directory.json show no HTTPS-related configuration. | N7: If the diagnosis file does not include install.ini or nodes-directory.json content, or if reverse-proxy setup is external to DSS, flag as needs_manual_review and confirm directly with the customer. | O7: HTTPS protects data in transit and is recommended practice for securing access to DSS. | P7: HTTPS, reverse proxy, install.ini, nodes-directory.json | Q7: security_permissions_compliance | R7: 5, 6 | S7: HTTPS | NICE TO HAVE; HTTPS | NICE TO HAVE (Review steps) | T7: medium | V7: Pass | W7: apps/dss/data_design/install.ini [server] has no native SSL settings (port=11000), but hsts-max-age=31536000 is set, and apps/dss/data_design/config/general-settings.json studioExternalUrl='https://design.ds.p4d.data.slb.com'. deployer/govern nodeUrls are also https. | X7: DSS does not terminate TLS itself. The bundle does reference an HTTPS external URL and sets HSTS, which is positive evidence that a TLS-terminating reverse proxy/LB sits in front of DSS. Confirm that plain HTTP on :11000 is not reachable from user networks (firewall), so HTTPS is truly enforced. | Y7: 2026-09-25 | Z7: Claude (AI-assisted review) - bundle dku_diagnosis_2026-07-22-08-21-05 (node p4d, DSS 14.4.3)
A8: SEC-007 | B8: nice_to_have | C8: qualitative_practice | D8: Security Model & Groups | E8: DSS Groups Security Model Appropriately Defined | F8: Confirm the client has an appropriate set of groups within their DSS security model: that they understand the DSS security model, that appropriate groups have been defined, and that permissions are properly granted based on those groups. | L8: Documentation or discussion notes indicate the customer has defined distinct DSS groups aligned to roles/functions, with permissions (project access, connections, etc.) granted based on group membership rather than ad hoc per-user grants. | M8: Evidence of a flat or minimal group structure, permissions granted broadly or per-individual-user without group-based structure, or customer confusion about the security model in review notes. | N8: A diagnosis file typically cannot show group design intent or customer understanding; flag as needs_manual_review and recommend a discussion with the client to assess this. | O8: A well-structured group model ensures permissions are manageable, auditable, and scalable as the platform grows. | P8: DSS groups, security model, permissions | Q8: security_permissions_compliance | R8: 7 | S8: DSS groups security model | NICE TO HAVE | T8: low | U8: Entirely a qualitative, discussion-based check with no technical pointer. | V8: Partial | W8: config/users.json: 25 users (11 DESIGNER, 9 AI_CONSUMER, 5 PLATFORM_ADMIN), 27 groups following a per-EAR <ear>_designer_local / <ear>_viewer_local pattern plus admin/data-scientist groups. Anomalies: Other_dssnp_ear-aa-21183_viewer_local and Other_dssnp_ear-aa-30051_viewer_local have mayCreateProjects and mayWriteSafeCode (same as designer groups); legacy 'data_team' has mayWriteUnsafeCode. | X8: The group model is structured and role-based (good). Some 'viewer' groups carry designer-level permissions, and the legacy local groups (data_team, readers) should be reviewed. Confirm the intended model with the customer. | Y8: 2026-09-25 | Z8: Claude (AI-assisted review) - bundle dku_diagnosis_2026-07-22-08-21-05 (node p4d, DSS 14.4.3)
A9: SEC-008 | B9: nice_to_have | C9: specific_setting | D9: LDAP Configuration | E9: LDAP Authorized Groups Configured | F9: Where DSS is integrated with LDAP, ensure Authorized Groups are configured so that only members of specified groups can connect; if LDAP is enabled but no Authorized Groups are set, all LDAP users matching the User filter query can connect, which should be flagged to the customer as a recommended improvement. | G9: {DATA_DIR}/config/general-settings.json > ldapSettings.authorizedGroups | H9: exists | I9: non-empty (populated with one or more groups) | K9: Check is conditional on ldapSettings.enabled being true. | L9: general-settings.json shows ldapSettings.enabled: true and authorizedGroups populated with one or more group entries; front-end equivalent shows Authorized groups field populated under Login (LDAP, SSO) & Security > Groups mapping. | M9: ldapSettings.enabled is true but authorizedGroups is empty or absent, meaning all LDAP users passing the User filter can connect without group-based restriction. | N9: If ldapSettings is not present or LDAP is not enabled, this check does not apply; if enabled but authorizedGroups status is unclear, flag as needs_manual_review. | O9: Authorized Groups restrict which LDAP-authenticated users may connect to DSS, reducing unauthorized access risk. | P9: LDAP, authorizedGroups, authentication | Q9: security_permissions_compliance | R9: 7, 8 | S9: LDAP: Authorized groups | NICE TO HAVE; LDAP: Authorized groups | NICE TO HAVE (Review steps) | T9: high | V9: Not Applicable | W9: apps/dss/data_design/config/general-settings.json ldapSettings.enabled=false (authorizedGroups is populated with 3 groups anyway). Login is via SSO: ssoSettings.enabled=true, protocol OPENID, authorizedGroups has 3 Azure AD group IDs. | X9: LDAP authentication is not enabled, so this check does not apply. The equivalent control exists on SSO: authorizedGroups is set on the OpenID config. | Y9: 2026-09-25 | Z9: Claude (AI-assisted review) - bundle dku_diagnosis_2026-07-22-08-21-05 (node p4d, DSS 14.4.3)
A10: SEC-009 | B10: nice_to_have | C10: qualitative_practice | D10: Single Sign-On | E10: SSO Enablement Reviewed | F10: Verify whether SSO is enabled for the DSS instance; if not, discuss with the customer whether enabling SSO would benefit their deployment. | L10: Configuration or documentation indicates SSO is enabled and integrated with the customer's identity provider. | M10: SSO is not configured and there is no record of a discussion with the customer about its potential benefits. | N10: Diagnosis files may not clearly expose SSO configuration; if unclear, flag as needs_manual_review and recommend confirming SSO status directly with the customer/admin settings. | O10: SSO can improve authentication security and user experience by centralizing identity management. | P10: SSO, authentication | Q10: security_permissions_compliance | R10: 8 | S10: SSO | NICE TO HAVE | T10: low | U10: No literal field path or diag pointer is given for SSO status in this document. | V10: Pass | W10: apps/dss/data_design/config/general-settings.json ssoSettings.enabled=true, protocol=OPENID, issuer=https://login.microsoftonline.com/41ff26dc-.../v2.0, usePKCE=true, enableGroups=true, authorizedGroups set. | X10: SSO via Azure AD (OIDC) is enabled, with PKCE and group-based authorisation. | Y10: 2026-09-25 | Z10: Claude (AI-assisted review) - bundle dku_diagnosis_2026-07-22-08-21-05 (node p4d, DSS 14.4.3)
A11: SEC-010 | B11: nice_to_have | C11: qualitative_practice | D11: Proxy Configuration | E11: Proxy Configuration Reviewed and Documented | F11: Take the opportunity to review and understand any proxy configuration in use, ensuring it is accurately documented in the platform tooling. | L11: Platform tooling/documentation contains accurate, up-to-date proxy configuration details matching the instance's actual proxy setup. | M11: Proxy configuration is undocumented, outdated, or inconsistent with the actual instance setup. | N11: A diagnosis file is unlikely to fully capture proxy configuration or the state of external documentation; flag as needs_manual_review to confirm with the customer and platform tooling records. | O11: Understanding and documenting proxy configuration helps ensure connectivity and troubleshooting information is accurate and available. | P11: proxy configuration, platform tooling | Q11: security_permissions_compliance | R11: 8 | S11: Proxy configuration | NICE TO HAVE | T11: low | U11: No technical pointer given; purely a documentation/understanding check. | V11: Needs Review | W11: apps/dss/data_design/config/general-settings.json proxySettings={port: 0} (no global DSS proxy set); azureADSettings.useGlobalProxy=true but Azure AD sync is disabled. | X11: No global HTTP proxy is configured in DSS. Confirm whether egress relies on a transparent/network proxy, and that the platform documentation reflects this. | Y11: 2026-09-25 | Z11: Claude (AI-assisted review) - bundle dku_diagnosis_2026-07-22-08-21-05 (node p4d, DSS 14.4.3)

Sheet Generative AI Acceleration & In
A1: id | B1: priority | C1: check_type | D1: subtopic | E1: title | F1: statement | G1: parameter_hint | H1: operator | I1: expected_value | J1: unit | K1: expected_condition_notes | L1: supporting_evidence | M1: contradicting_evidence | N1: insufficient_evidence_handling | O1: rationale | P1: dataiku_concepts | Q1: source_document | R1: source_page | S1: source_section | T1: confidence | U1: ambiguity_notes | V1: validation_status | W1: evidence_found | X1: notes | Y1: validated_at | Z1: validated_by
A2: GENAI-001 | B2: must_have | C2: specific_setting | D2: LLM Mesh and Agents | E2: Internal Code Environments for RAG, Document Extraction, PII Detection | F2: Ensure the internal code environments for Retrieval-Augmented Generation, document extraction, and PII detection are properly installed and set as the default code-env for each category under Administration > Settings > Other > LLM Mesh. If a non-internal code-env is used instead, DSS surfaces a warning in the LLM Mesh settings page and in Administration > Code-envs > Internal envs. | G2: general-settings.json > generativeAISettings > defaultRetrievableKnowledgeCodeEnv | H2: not_exists | I2: absent (i.e., using internal default code-env, containerMode NONE) | K2: If defaultRetrievableKnowledgeCodeEnv is present with a custom value and containerMode is INHERIT, a non-internal code-env is in use. Also check presidioBasedPIIDetection (PII detection) and embedDocumentsRecipeSettings (document extraction) keys for equivalent non-internal overrides. | L2: general-settings.json generativeAISettings shows containerMode NONE with no defaultRetrievableKnowledgeCodeEnv key, and PII/doc extraction sections show no custom code-env overrides; Admin > Code-envs > Internal envs shows RAG/PII/Doc extraction set up as internal. | M2: defaultRetrievableKnowledgeCodeEnv key present with a non-internal value, containerMode INHERIT, or a warning banner shown in Admin > Settings > Other > LLM Mesh / Code-envs > Internal envs. | N2: If generativeAISettings section is absent from the diagnosis, flag needs_manual_review to check the UI directly. | O2: Internal code envs bundle the correct/supported dependencies (e.g., libreoffice for document extraction); using a non-internal env can cause missing dependencies or unsupported behavior. | P2: LLM Mesh, code environments, RAG, PII detection, document extraction | Q2: generative_ai_acceleration | R2: 1, 2, 3 | S2: LLM Mesh and Agents MUST HAVE:; RAG, Doc extraction, PII detection; Instance Diags / DiagParser3 | T2: high | V2: Pass | W2: apps/dss/data_design/config/general-settings.json generativeAISettings: defaultRetrievableKnowledgeCodeEnv='INTERNAL_retrieval_augmented_generation_v1', presidioBasedPIIDetectionCodeEnv='INTERNAL_pii_detection_v1', embedDocumentsRecipeSettings (no custom env). code_envs_desc_listing.txt contains INTERNAL_retrieval_augmented_generation_v1, INTERNAL_pii_detection_v1 and INTERNAL_document_extraction_v1. | X2: The keys are present, but they explicitly point to Dataiku's INTERNAL_* envs, not custom ones, which meets the intent. containerMode=INHERIT means these run with the global default (currently local, since defaultExecutionConfig is empty; see ARCH-016). Double-check that no warning banner shows in Admin > Code envs > Internal envs. | Y2: 2026-09-25 | Z2: Claude (AI-assisted review) - bundle dku_diagnosis_2026-07-22-08-21-05 (node p4d, DSS 14.4.3)
A3: GENAI-002 | B3: must_have | C3: specific_setting | D3: LLM Mesh and Agents | E3: Hugging Face Local LLM Enablement (Conditional) | F3: When the customer uses Hugging Face local LLMs, ensure the INTERNAL_huggingface_local_v1 code env is installed and that technical prerequisites are met: a running Elastic AI Kubernetes cluster with NVIDIA GPUs (compute capability >= 7.0, driver compatible with CUDA 12.8), Almalinux 9 base images, and Python 3.11. | G3: Administration > Code-envs > INTERNAL_huggingface_local_v1 (installed) | H3: exists | I3: installed and configured | K3: No literal diag JSON field was given in the source for this check; infrastructure prerequisites (GPU compute capability, CUDA/driver version, Python 3.11, Almalinux 9) are not verifiable from a diagnosis JSON alone and require manual/infra review. | L3: Code-env listing shows INTERNAL_huggingface_local_v1 present and in use; Elastic AI cluster configuration references GPU-enabled nodes. | M3: Env missing, or Hugging Face local LLM feature is referenced in use without a corresponding GPU-enabled Elastic AI cluster. | N3: If the diagnosis doesn't reference Hugging Face local LLM usage, treat as not applicable; if usage is confirmed elsewhere but infra details aren't in the diagnosis, flag needs_manual_review. | O3: Without the correct GPU cluster, driver/CUDA compatibility, base image, and Python version, local Hugging Face LLMs will not function. | P3: Hugging Face, Elastic AI, Kubernetes, GPU, code environments | Q3: generative_ai_acceleration | R3: 3 | S3: Hugging face local LLMs (only if applicable) | T3: medium | U3: Conditional feature ('only if applicable'); priority applies only when the customer has opted to use this capability. | V3: Not Applicable | W3: code_envs_desc_listing.txt: no INTERNAL_huggingface_local_v1. apps/dss/data_design/config/general-settings.json generativeAISettings.huggingFaceLocalSettings holds only defaults (maxConcurrentKernels=2). | X3: No evidence that local Hugging Face LLMs are used. If they are planned, note that the GPU container configs reference a missing 13.4.2 GPU image (see ARCH-010) and that base images are built with py39 only (Python 3.11 is required). | Y3: 2026-09-25 | Z3: Claude (AI-assisted review) - bundle dku_diagnosis_2026-07-22-08-21-05 (node p4d, DSS 14.4.3)
A4: GENAI-003 | B4: must_have | C4: specific_setting | D4: Trace Explorer | E4: Trace Explorer Default Configuration | F4: Configure Trace Explorer via Administration > Settings > Other > LLM Mesh > Configuration > Trace by setting a default Project and Trace Explorer webapp instance, so the 'view traces' shortcut is functional from Prompt Studio, Agents, and Retrieval-Augmented LLMs. | G4: general-settings.json > llmTraceSettings.traceExplorerDefaultWebApp | H4: exists | I4: projectKey and webAppId both set to non-empty values | L4: llmTraceSettings.traceExplorerDefaultWebApp present in general-settings.json with non-empty projectKey and webAppId fields. | M4: llmTraceSettings missing entirely, or traceExplorerDefaultWebApp present but empty/null. | N4: If general-settings.json content isn't captured in the diagnosis, flag needs_manual_review to verify via the UI. | O4: Without this default configuration, the trace-viewing shortcut from Prompt Studio/Agents/RAG LLMs will not function. | P4: Trace Explorer, LLM Mesh, Agents | Q4: generative_ai_acceleration | R4: 3, 4 | S4: Trace Explorer MUST HAVE:; Instance Diags / DiagParser3 | T4: high | V4: Fail | W4: apps/dss/data_design/config/general-settings.json generativeAISettings.llmTraceSettings.traceExplorerDefaultWebApp={} (empty). The traces-explorer plugin is installed (config/plugins/traces-explorer). | X4: The Trace Explorer plugin is installed and LLM Mesh is in heavy use (9 AzureOpenAI connections, cost quotas), but no default project/webapp is set, so 'View traces' shortcuts will not work. Create a Trace Explorer webapp and set it in Admin > Settings > LLM Mesh > Trace. | Y4: 2026-09-25 | Z4: Claude (AI-assisted review) - bundle dku_diagnosis_2026-07-22-08-21-05 (node p4d, DSS 14.4.3)
A5: GENAI-004 | B5: nice_to_have | C5: specific_setting | D5: AI Services | E5: AI Services Terms of Use Acceptance & Enablement | F5: Verify that the customer has accepted the Dataiku AI Services Terms of Use and that AI Services are enabled by the admin in Administration > AI Services. Confirm outbound internet connectivity to https://ai-gateway.api-services.dataiku.io, required in both 'Operated by Dataiku' and 'Bring your own LLM' modes. | G5: general-settings.json > dataikuAIServicesTermsOfUseAccepted / enabled | H5: equals | I5: true | K5: Also check byoTermsOfUseAccepted for Bring-your-own-LLM mode. Internet whitelisting of ai-gateway.api-services.dataiku.io is not verifiable from diagnosis JSON alone. | L5: general-settings.json shows dataikuAIServicesTermsOfUseAccepted=true and enabled=true. | M5: enabled=false or Terms of Use not accepted while AI Services usage is expected/observed. | N5: If AI Services keys are absent from the diagnosis, treat as not enabled and flag needs_manual_review to confirm with the customer whether AI Services usage is intended. | P5: AI Services, Terms of Use, LLM Mesh | Q5: generative_ai_acceleration | R5: 4, 5 | S5: AI Services NICE TO HAVE:; Instance Diags / DiagParser3 | T5: high | V5: Needs Review | W5: apps/dss/data_design/config/general-settings.json aiDrivenAnalyticsSettings: dataikuAIServicesTermsOfUseAccepted=false, enabled=false. askDataikuSettings.enabled=true; codeAssistantSettings.codeAssistantEnabled=false. | X5: Dataiku AI Services are not accepted or enabled. That is acceptable if not wanted (this is nice-to-have). Confirm intent with the customer, and if enabling, confirm outbound access to ai-gateway.api-services.dataiku.io. | Y5: 2026-09-25 | Z5: Claude (AI-assisted review) - bundle dku_diagnosis_2026-07-22-08-21-05 (node p4d, DSS 14.4.3)
A6: GENAI-005 | B6: must_have | C6: specific_setting | D6: Bring Your Own LLM Mode | E6: Bring Your Own LLM Mode - Reference Project & Main Model | F6: When Bring Your Own LLM mode is active, a Reference project key must be set (used for LLM Mesh requests running outside a DSS project, e.g. AI Search) and a main LLM model must be configured; if unset, requests will fail. | G6: general-settings.json > localAIServerSettings.referenceProjectKey / mainLLMId | H6: exists | I6: non-empty values set for both fields | L6: localAIServerSettings.useLocalServer=true with referenceProjectKey and mainLLMId populated (e.g., 'openai:openai-adrissi:gpt-5.5'). | M6: useLocalServer=true but referenceProjectKey or mainLLMId missing or empty. | N6: If localAIServerSettings is absent from the diagnosis, flag needs_manual_review to confirm whether Bring Your Own LLM mode is in use. | P6: Bring Your Own LLM, AI Services, LLM Mesh | Q6: generative_ai_acceleration | R6: 5, 6 | S6: Bring your own LLM Mode; Instance Diags / DiagParser3 | T6: high | V6: Not Applicable | W6: apps/dss/data_design/config/general-settings.json localAIServerSettings.useLocalServer=false. | X6: Bring Your Own LLM mode is not active. | Y6: 2026-09-25 | Z6: Claude (AI-assisted review) - bundle dku_diagnosis_2026-07-22-08-21-05 (node p4d, DSS 14.4.3)
A7: GENAI-006 | B7: nice_to_have | C7: specific_setting | D7: Bring Your Own LLM Mode | E7: Bring Your Own LLM - Recommended Model Versions | F7: If the customer has activated Bring Your Own LLM Mode for AI Assistants, verify they are using recommended model versions (minimum OpenAI ChatGPT 5.2) and avoid unsupported ones (e.g., ChatGPT 5.1, which will not provide good results). | G7: general-settings.json > localAIServerSettings.mainLLMId (and responseFormatAwareLLMId/fastLightLLMId) | H7: not_equals | I7: ChatGPT 5.1 or earlier / unsupported model versions | K7: Exact version comparison against the recommended minimum (ChatGPT 5.2) may require manual judgment; refer to https://doc.dataiku.com/dss/latest/ai-assistants/setup.html#bring-your-own-llm-mode. | L7: mainLLMId/related LLM IDs reference gpt-5.2 or later. | M7: mainLLMId/related LLM IDs reference gpt-5.1 or an older/unsupported model. | N7: If the model identifier is ambiguous, non-OpenAI, or version cannot be determined, flag needs_manual_review and reference the setup documentation. | O7: Using unsupported model versions is stated to produce poor results. | P7: Bring Your Own LLM, Model selection, AI Assistants | Q7: generative_ai_acceleration | R7: 6, 7 | S7: Bring your own LLM Mode; Bring your own LLM Mode | T7: medium | V7: Not Applicable | W7: apps/dss/data_design/config/general-settings.json localAIServerSettings.useLocalServer=false. | X7: BYO LLM mode is not active, so there is no model-version check. | Y7: 2026-09-25 | Z7: Claude (AI-assisted review) - bundle dku_diagnosis_2026-07-22-08-21-05 (node p4d, DSS 14.4.3)
A8: GENAI-007 | B8: must_have | C8: specific_setting | D8: Cobuild | E8: Cobuild Default LLM Configuration | F8: Administrators must configure default LLM settings for Cobuild (agent-building tools) upon activation of AI Assistants, including defaultEmbeddingLLMId, defaultLLMId, and defaultImageGenerationLLMId under agentBuildingSettings; if unset, Cobuild's building-agent tools will fail and instruct users to contact an administrator. | G8: general-settings.json > aiDrivenAnalyticsSettings.agentBuildingSettings.{defaultEmbeddingLLMId, defaultLLMId, defaultImageGenerationLLMId} | H8: exists | I8: all three fields populated with valid LLM IDs | L8: agentBuildingSettings block shows non-empty defaultEmbeddingLLMId, defaultLLMId, and defaultImageGenerationLLMId values. | M8: One or more of these fields is missing or empty while Cobuild/AI Assistants is enabled. | N8: If aiDrivenAnalyticsSettings is absent from the diagnosis, flag needs_manual_review to confirm whether Cobuild/AI Assistants is enabled for this customer. | P8: Cobuild, AI Assistants, Agent building | Q8: generative_ai_acceleration | R8: 7, 8, 9 | S8: Cobuild; Cobuild; Instance Diags / DiagParser3 | T8: high | V8: Not Applicable | W8: apps/dss/data_design/config/general-settings.json aiDrivenAnalyticsSettings.enabled=false; no agentBuildingSettings block. | X8: AI Assistants/Cobuild are not activated on this 14.4.3 instance. Revisit after the 15.x upgrade if Cobuild is enabled. | Y8: 2026-09-25 | Z8: Claude (AI-assisted review) - bundle dku_diagnosis_2026-07-22-08-21-05 (node p4d, DSS 14.4.3)
A9: GENAI-008 | B9: must_have | C9: qualitative_practice | D9: AI Assistants Diagnostics | E9: Include AI Assistant Debug Data in Instance Diagnostics | F9: To access AI Assistant Logs (ui.json, runtime.json, traces per project) in an Instance Diagnostic (V14.7+), an administrator must explicitly select the option to include these logs when generating a diagnostic via Administration > Maintenance > Instance Diagnostic. | L9: The diagnostic bundle includes an 'AI Assistants debug data' section organized by project with ui.json, runtime.json, and traces files. | M9: Diagnostic bundle lacks these files despite AI Assistants being actively used on the instance. | N9: If the diagnostic was generated on a version prior to 14.7, or the inclusion option's state can't be determined, flag needs_manual_review and note reviewers should confirm the option was selected during diagnostic generation. | O9: Without selecting this option, AI Assistant logs are not captured, limiting the reviewer's ability to diagnose LLM Mesh/agent-building issues. | P9: Instance Diagnostic, AI Assistants, Logging | Q9: generative_ai_acceleration | R9: 9, 10 | S9: Instance Diags / DiagParser3; Instance Diags / DiagParser3 | T9: low | U9: This is more a diagnostic-generation process note than a platform configuration state, so evaluability from a static diagnosis file is limited. | V9: Not Applicable | W9: apps/dss/data_design/dss-version.json product_version=14.4.3 (<14.7). AI Assistants disabled (aiDrivenAnalyticsSettings.enabled=false). | X9: The option to include AI Assistant debug data does not exist before 14.7, and AI Assistants are not in use. After upgrading, tick the option when generating diagnostics. | Y9: 2026-09-25 | Z9: Claude (AI-assisted review) - bundle dku_diagnosis_2026-07-22-08-21-05 (node p4d, DSS 14.4.3)
A10: GENAI-009 | B10: nice_to_have | C10: qualitative_practice | D10: Agent Hub | E10: Agent Hub Deployment Required Permissions | F10: Before a user can deploy an Agent Hub instance, they must have permissions for writing project content in the hosting project, writing isolated code execution, WebApp impersonation, and (if Quick agents are enabled) create projects; alternatively the user could be a DSS administrator, though a dedicated service account is preferred. | L10: Administration > Security > Groups shows the Agent Hub deployer's group granted 'Write project content', 'Write isolated code execution', and 'WebApp impersonation' permissions (plus 'Create projects' if Quick agents are enabled), or the deployer is a DSS admin/service account. | M10: The deployer's group lacks one or more of these permissions and is not an admin/service account, or logs show 'Not authorized' errors when creating the Agent Hub WebApp. | N10: If the diagnosis file lacks per-user/group permission detail, flag needs_manual_review and recommend checking Administration > Security > Groups directly. | O10: Missing permissions cause deployment failures such as 'Not authorized' errors when creating the Agent Hub WebApp. | P10: Agent Hub, Permissions, Groups, WebApp | Q10: generative_ai_acceleration | R10: 10, 11, 12 | S10: Agent Hub NICE TO HAVE:; Writing isolated code execution; WebApp impersonation | T10: medium | U10: Although the parent topic is tagged NICE TO HAVE, the described permission requirements are phrased as mandatory ('must have permissions') for successful deployment; classification follows the explicit heading tag. | V10: Not Applicable | W10: config_listing.txt: no Agent Hub plugin/webapp (plugins present include ai-agent-plugin, agent-connect, traces-explorer, but not agent-hub). | X10: Agent Hub is not deployed on this instance. | Y10: 2026-09-25 | Z10: Claude (AI-assisted review) - bundle dku_diagnosis_2026-07-22-08-21-05 (node p4d, DSS 14.4.3)
A11: GENAI-010 | B11: nice_to_have | C11: qualitative_practice | D11: Agent Hub | E11: Use Service Account for Agent Hub Management | F11: Dataiku recommends using a dedicated service account rather than an instance administrator account to manage and configure an Agent Hub instance. | L11: Agent Hub is managed/configured by a dedicated service account (non-admin) holding the specific required permissions rather than by a full instance administrator. | M11: Agent Hub is managed exclusively using a full instance administrator account. | N11: If the diagnosis doesn't identify the account type managing Agent Hub, flag needs_manual_review. | O11: Reduces privilege exposure by avoiding routine use of full instance administrator accounts for Agent Hub management. | P11: Agent Hub, Service account, Least privilege | Q11: generative_ai_acceleration | R11: 10 | S11: Required permissions before deployment | T11: medium | V11: Not Applicable | W11: No Agent Hub plugin/webapp found in config_listing.txt. | X11: Agent Hub is not deployed. | Y11: 2026-09-25 | Z11: Claude (AI-assisted review) - bundle dku_diagnosis_2026-07-22-08-21-05 (node p4d, DSS 14.4.3)
A12: GENAI-011 | B12: nice_to_have | C12: specific_setting | D12: Agent Hub | E12: Agent Hub WebApp Impersonation - Allowed Groups Scope | F12: For the group running the Agent Hub WebApp, configure the 'Allowed groups' field under Impersonation in WebApps (Administration > Security > Group) to include only the specific groups of users who should access Agent Hub; avoid using '.*' to allow impersonation of all groups, reserving that only for testing in a sandbox environment. | G12: Administration > Security > Group > Impersonation in WebApps > Allowed groups | H12: not_equals | I12: .* | K12: Conceptual UI-based pointer; no literal diagnosis JSON field was given in the source for this setting. | L12: Allowed groups field lists specific named groups relevant to Agent Hub users rather than a wildcard. | M12: Allowed groups field is set to '.*' in what appears to be a production environment. | N12: If group impersonation settings are not captured in the diagnosis, flag needs_manual_review and recommend checking Administration > Security > Group directly. | O12: Using '.*' allows impersonation of all groups, an overly broad security exposure outside of sandbox/testing contexts. | P12: Agent Hub, Impersonation, WebApps, Security groups | Q12: generative_ai_acceleration | R12: 12 | S12: WebApp impersonation | T12: medium | V12: Not Applicable | W12: No Agent Hub plugin/webapp found in config_listing.txt. | X12: Agent Hub is not deployed. (Group-level WebApp impersonation 'Allowed groups' could not be inspected; groups.json is not in the bundle.) | Y12: 2026-09-25 | Z12: Claude (AI-assisted review) - bundle dku_diagnosis_2026-07-22-08-21-05 (node p4d, DSS 14.4.3)

Sheet Scalable Performance, Stability
A1: id | B1: priority | C1: check_type | D1: subtopic | E1: title | F1: statement | G1: parameter_hint | H1: operator | I1: expected_value | J1: unit | K1: expected_condition_notes | L1: supporting_evidence | M1: contradicting_evidence | N1: insufficient_evidence_handling | O1: rationale | P1: dataiku_concepts | Q1: source_document | R1: source_page | S1: source_section | T1: confidence | U1: ambiguity_notes | V1: validation_status | W1: evidence_found | X1: notes | Y1: validated_at | Z1: validated_by
A2: SCALE-001 | B2: must_have | C2: specific_setting | D2: Runtime Database | E2: External PostgreSQL Runtime Database | F2: The default H2 runtime database is not production-ready and should be replaced with an external PostgreSQL database (or DCS-managed internal PostgreSQL) for scalability and resilience. When PostgreSQL is used, connection pooling and backup practices must also be verified. | G2: general-settings.json > internalDatabase.type | H2: equals | I2: PostgreSQL | K2: Also verify maxPooledExternalConnections (general-settings.json) is at least 2x the postgresql.conf max_connections value (Cloud Stacks default max_connections=500), and that a backup process synced with DSS backups exists. | L2: general-settings.json shows internalDatabase.type = PostgreSQL (external or DCS-managed); maxPooledExternalConnections >= 2x postgres max_connections; documented backup process aligned with DSS backups. | M2: internalDatabase field absent or shows internal H2 in use without an external Postgres configured; maxPooledExternalConnections too low relative to max_connections; no DB backup process. | N2: If general-settings.json is unavailable or DB type cannot be determined, flag needs_manual_review and request the customer's postgresql.conf max_connections value and backup policy. | O2: H2 does not scale well and complicates backup/resilience; PostgreSQL is required for production readiness. | P2: runtime database, PostgreSQL, H2, backup | Q2: scalable_performance_ops | R2: 1, 2 | S2: Postgres runtime database | MUST HAVE; Postgres runtime database | MUST HAVE | T2: high | V2: Fail | W2: apps/dss/data_design/config/general-settings.json internalDatabase has only pool settings (maxPooledExternalConnections=50) and no external connection/type. datadir_listing.txt: H2 files actively written in apps/dss/data_design/databases/, e.g. jobs.mv.db (106.7MB, modified Jul 22 06:35), dss_usage.mv.db (45.8MB), flow_state.mv.db, persistent_notifications.mv.db. | X2: The runtime DB is still the embedded H2, which is not production-grade for a 25-user instance. Migrate to an external PostgreSQL. Set maxPooledExternalConnections to at least 2x Postgres max_connections, and align DB backups with DSS backups (SCALE-005). | Y2: 2026-09-25 | Z2: Claude (AI-assisted review) - bundle dku_diagnosis_2026-07-22-08-21-05 (node p4d, DSS 14.4.3)
A3: SCALE-002 | B3: nice_to_have | C3: specific_setting | D3: Metastore Configuration | E3: Appropriate Metastore Configured | F3: An appropriate metastore should be configured based on environment: Hive for standard Hadoop clusters, Glue when properly integrated on AWS, or the DSS internal metastore otherwise. Confirm the configured flavor matches the environment and that managed datasets sync correctly. | G3: general-settings.json > metastoreCatalogsSettings.flavor | H3: one_of | I3: Hive (Hadoop cluster) | Glue (AWS with proper integration) | DSS internal (otherwise) | K3: Correct value is context-dependent on infrastructure; also verify via Administration > Settings > Metastore catalogs UI. | L3: flavor value matches environment type (Hive for Hadoop, Glue for properly-integrated AWS, else DSS internal); a test dataset sync confirms managed datasets sync to the metastore. | M3: flavor mismatched with environment (e.g., Glue configured without proper AWS integration, or DSS internal used when Hive/Glue would be appropriate); sync test fails. | N3: If environment type or metastoreCatalogsSettings is not present in the diagnosis, flag needs_manual_review and confirm with the customer during interview. | O3: Correct metastore selection ensures managed dataset metadata is properly synced and available for query engines. | P3: metastore, Hive, Glue, managed datasets | Q3: scalable_performance_ops | R3: 2, 3 | S3: Metastore is configured | NICE TO HAVE; Metastore is configured | NICE TO HAVE | T3: medium | U3: Expected flavor value is not a fixed constant but depends on customer's infrastructure, so the check requires contextual knowledge of the environment. | V3: Fail | W3: apps/dss/data_design/config/general-settings.json metastoreCatalogsSettings.synchronizeTo.flavor=HIVESERVER2. hadoopSettings has no Hadoop/Kerberos; clusters/P4D.json hiveSettings hiveServer2Host=127.0.0.1. Cloud connections use metastoreSynchronizationMode=NO_SYNC. backend.log*: 'Spark fast-path status: Hadoop support not enabled on connection'. | X3: The instance is a GCP/Kubernetes deployment with no Hadoop cluster, yet the metastore is set to HiveServer2 (pointing at localhost). The expected setting is the DSS internal metastore. Confirm no Hive metastore actually exists, then switch the flavor to DSS internal and test a managed-dataset sync. | Y3: 2026-09-25 | Z3: Claude (AI-assisted review) - bundle dku_diagnosis_2026-07-22-08-21-05 (node p4d, DSS 14.4.3)
A4: SCALE-003 | B4: nice_to_have | C4: specific_setting | D4: Graphics Export | E4: Graphics Export (PDF/Image) Configuration | F4: Check whether PDF/image export from the Flow is configured; if not configured, discuss with the client whether this feature should be enabled. | G4: general-settings.json > graphicsExportsEnabled | H4: equals | I4: true | K4: Desired state is contextual on client needs; can also confirm via the Flow Actions > Export to PDF/Image UI option. | L4: graphicsExportsEnabled=true in general-settings.json, or the Export to PDF/Image option is visible in the Flow Actions menu. | M4: graphicsExportsEnabled=false with no documented discussion or decision with the client about whether the feature is desired. | N4: If the field is absent from the diagnosis, flag needs_manual_review and verify via the UI or ask the customer. | O4: Feature must be explicitly configured; disabling it may be acceptable if the client doesn't need it, hence nice to have. | P4: graphics export, Flow | Q4: scalable_performance_ops | R4: 3 | S4: Graphics export configured | NICE TO HAVE | T4: high | V4: Needs Review | W4: apps/dss/data_design/config/general-settings.json graphicsExportsEnabled=false. | X4: Flow/dashboard PDF and image export is not configured. Ask the client whether they want it. It needs the graphics-export setup (Chrome/deps) on the host. | Y4: 2026-09-25 | Z4: Claude (AI-assisted review) - bundle dku_diagnosis_2026-07-22-08-21-05 (node p4d, DSS 14.4.3)
A5: SCALE-004 | B5: must_have | C5: qualitative_practice | D5: Maintenance & Cleanup | E5: Admin Project for Garbage Collection | F5: An admin project should be set up to automatically clean up accumulated logs and idle Jupyter kernels on a schedule, per the Setup Maintenance Jobs wiki. | L5: Presence of a dedicated admin/maintenance project with scenarios scheduled to clean logs and idle kernels; scenario run history shows regular execution. | M5: No maintenance project exists, or disk usage/log data shows unbounded growth of logs or idle Jupyter kernels. | N5: If the diagnosis doesn't include a project list or scenario details, flag needs_manual_review and ask the customer to confirm existence of a scheduled cleanup project. | O5: Without cleanup, logs and idle kernels accumulate over time causing resource exhaustion. | P5: admin project, garbage collection, scenarios, disk usage | Q5: scalable_performance_ops | R5: 3, 4 | S5: Admin project - garbage collection | MUST HAVE; Admin project - garbage collection | MUST HAVE | T5: medium | V5: Fail | W5: config_listing.txt: ADMINISTRATIONPROJECT exists with scenarios CERTIFICATE_EXPIRATION, Schedule_build_of__expiring_cert_ and PROJECT_REPORT only; no log-cleanup or idle-kernel cleanup scenario in any project. backend.log*: 17,661x 'Failed to build trigger runner (ADMINISTRATIONPROJECT.Schedule_build_of__expiring_cert_...): configured to run as user 'ds10' which does not exist'. | X5: An admin project exists but has no garbage-collection scenarios, and its one scheduled scenario is broken (its run-as user was deleted). Add scheduled macros for old job logs/scenario runs, idle Jupyter kernels and temp files per the Setup Maintenance Jobs wiki, and fix the run-as user. Log volume is high: backend/nginx/ipython logs rotate at 100MB. | Y5: 2026-09-25 | Z5: Claude (AI-assisted review) - bundle dku_diagnosis_2026-07-22-08-21-05 (node p4d, DSS 14.4.3)
A6: SCALE-005 | B6: must_have | C6: qualitative_practice | D6: Backup & Recovery | E6: Environment Backup Policy | F6: Routine backups of DSS data must be configured for every DSS node to ensure data availability; for DCS installs, verify via Fleet Manager Instances > Settings > Snapshots, and for custom installs request backup policy details directly from the client. | L6: For DCS: Fleet Manager > Instances > Settings > Snapshots shows a scheduled snapshot policy. For custom installs: a documented backup policy/cron job covering the DSS data directory is provided by the customer. | M6: No snapshot schedule configured in Fleet Manager, or the customer has no documented backup process for a custom install. | N6: If backup configuration isn't visible in the diagnosis (common for custom installs), flag needs_manual_review and request the client's backup policy documentation. | O6: Backups ensure business continuity and data availability in case of failure. | P6: backup, Fleet Manager, snapshots | Q6: scalable_performance_ops | R6: 4, 5 | S6: Environment Backup | MUST HAVE; Environment Backup | MUST HAVE | T6: medium | V6: Needs Review | W6: Custom install on a GCP VM (/apps/dss/data_design on /dev/mapper/vg01-vol01, 800G, 74% used). No backup or snapshot configuration is visible in the bundle. | X6: Ask the customer for the backup policy (GCP PD snapshots or file-level backup of DATA_DIR, including the H2 databases until the Postgres migration). Confirm frequency, retention and a tested restore. | Y6: 2026-09-25 | Z6: Claude (AI-assisted review) - bundle dku_diagnosis_2026-07-22-08-21-05 (node p4d, DSS 14.4.3)
A7: SCALE-006 | B7: nice_to_have | C7: qualitative_practice | D7: Instance Sanity Check | E7: Usage of Instance Sanity Check | F7: Verify that the Instance Sanity Check feature is used to detect instance configuration problems, accessible via Administration > Maintenance > Instance Sanity Check. | L7: Evidence that the customer has run the Instance Sanity Check periodically and addressed reported issues (e.g., DiagParser3 sanity check output showing no unresolved critical issues). | M7: No record of Instance Sanity Check usage, or reported issues left unresolved for extended periods. | N7: If the diagnosis doesn't include sanity check results, flag needs_manual_review and check DiagParser3 or the Administration UI directly. | O7: Regular use helps proactively detect instance configuration issues before they cause problems. | P7: Instance Sanity Check | Q7: scalable_performance_ops | R7: 5, 6 | S7: Usage of Instance Sanity Check | NICE TO HAVE; Usage of Instance Sanity Check | NICE TO HAVE | T7: medium | V7: Partial | W7: apps/dss/data_design/run/sanity-check.json: lastRunTimestamp=2026-07-22 08:29:52 UTC (run automatically by the diagnosis), maxSeverity=WARNING, 9 warnings still open: 6x process types without memory limit, rotational disk, Spark details-read gap on ear27331_blob_stg_1, missing base image dataiku-exec-gpu:13.4.2. apps/dss/data_design/config/general-settings.json sanityCheckExclusionList=[]. | X7: The sanity check runs, but its warnings are unresolved, including one left over from the 13.4.2 era, which suggests nobody reviews it regularly. Add a periodic sanity-check review (or scenario) and clear the open items (SEC-004, ARCH-004, SCALE-012, ARCH-010). | Y7: 2026-09-25 | Z7: Claude (AI-assisted review) - bundle dku_diagnosis_2026-07-22-08-21-05 (node p4d, DSS 14.4.3)
A8: SCALE-007 | B8: must_have | C8: qualitative_practice | D8: Log Monitoring | E8: Backend.log Error Review | F8: Review recent backend.log files (including rotated/zipped logs) for ERROR or FATAL level entries indicating systemic issues such as repeating stack traces, connection failures, or plugin crashes; investigate patterns that recur frequently even without explicit user complaints. | L8: backend.log and rotated logs show few or no ERROR/FATAL entries, or only isolated non-recurring errors; AI Log Analysis in DiagParser3 shows no systemic issue flagged. | M8: Frequent recurring ERROR/FATAL entries (e.g., the same stack trace dozens of times per day), repeated connection failures, or plugin crashes. | N8: If logs aren't included or available in the diagnosis bundle, flag needs_manual_review and request the backend.log files directly. | O8: A high volume of repeated errors often points to a systemic issue that needs to be addressed before it impacts instance stability. | P8: backend.log, AI Log Analysis, DiagParser3 | Q8: scalable_performance_ops | R8: 6, 7 | S8: Backend.log Errors | MUST HAVE; Backend.log Errors | MUST HAVE | T8: high | V8: Fail | W8: backend.log.2/.1/.0 (2026-07-16 to 2026-07-22): about 167k ERROR lines. Top: 123,032 dku.unifiedmonitoring.systemMonitoringService 'Error parsing graphite line: <deployment>-on-PND_Local.memoryCapacityMB/cpuCapacityMillis' (4,394 per metric); 35,322 dip.scenarios.trigger.service 'Failed to build trigger runner ... configured to run as user 'ds10'/'vgupta11' which does not exist'; 6,840 dip.controllers 'Unknown execution context: code-studio-as-webapp-...'; 878 activityMonitoringService 'Couldn't write activity metrics ... sample_API-on-PND_Local'; 30 'Could not stop Kubernetes deployment'. No OutOfMemoryError in current backend logs. | X8: Several systemic, recurring errors: (1) unified-monitoring graphite parsing and RRD writes for API deployments on an old 'PND_Local' infra (stale deployments or monitoring entries; clean up or fix); (2) scenarios whose run-as users (ds10, vgupta11) no longer exist (reassign or disable; see SCALE-004); (3) orphaned code-studio webapp executions calling back (clean up stale K8s code-studio deployments; see ARCH-012). None crashes DSS on its own, but together they flood the logs and hide real problems. | Y8: 2026-09-25 | Z8: Claude (AI-assisted review) - bundle dku_diagnosis_2026-07-22-08-21-05 (node p4d, DSS 14.4.3)
A9: SCALE-008 | B9: must_have | C9: specific_setting | D9: Memory Sizing | E9: Backend Xmx Sizing | F9: backend.xmx must be appropriately sized for the deployment based on system memory (Cloud Stacks heuristic: 4g for >12GB RAM, 8g for >30GB RAM, 16g for >95GB RAM, more for larger deployments), and should be at least 3x the size of the configuration folder. jek.xmx and fek.xmx should also be checked to ensure they haven't been oversized, and backend.log should be checked for OutOfMemoryError entries. | G9: install.ini > backend.xmx | H9: greater_than_or_equal | I9: per Cloud Stacks heuristic tier (4g/8g/16g based on system RAM) and >=3x config folder size | J9: GB | K9: Also verify jek.xmx/fek.xmx are not oversized, and that xmx avoids the 32GB<=xmx<48GB dead zone (jump to 48GB instead) due to Java Ordinary Object Pointer behavior. | L9: install.ini backend.xmx matches or exceeds the recommended tier for system memory, is >=3x config folder size, and avoids the 32-48GB dead zone; no OutOfMemoryError entries in backend.log. | M9: backend.xmx set below the recommended heuristic, falls in the 32GB-48GB dead zone, or backend.log shows recurring 'OutOfMemoryError: Java heap space' / 'OutOfMemoryError: GC Overhead limit exceeded' entries. | N9: If install.ini or system memory info is not present in the diagnosis, flag needs_manual_review and request system specs and install.ini contents. | O9: Insufficient or misconfigured heap sizing leads to OutOfMemory errors and instability; oversizing into the 32-48GB range paradoxically reduces available memory due to JVM pointer compression behavior. | P9: backend.xmx, jek.xmx, fek.xmx, JVM memory, OutOfMemoryError | Q9: scalable_performance_ops | R9: 7, 8 | S9: Backend Xmx | MUST HAVE; Backend Xmx | MUST HAVE | T9: high | V9: Pass | W9: apps/dss/data_design/install.ini [javaopts] backend.xmx=8g. Host RAM about 62GB (>30GB tier -> 8g). Config folder about 193MB (config_listing.txt), so 3x is about 0.6GB. Not in the 32-48GB range. JEK Xmx=2g (hs_err_pid1650445). No OutOfMemoryError in backend.log/.1/.2. Historic crashes: hs_err_pid2859808 (2025-02-25, backend, 'Requested array size exceeds VM limit'); hs_err_pid1650445 (2025-12-23, JEK, 'Java heap space'); hs_err_pid5201 (2026-03-28, backend) and hs_err_pid2976607 (2026-07-21, JVM start) are native mmap failures ('insufficient memory ... system is out of physical RAM or swap'). | X9: The heap size meets the heuristic. The two most recent crashes are not heap-sizing problems: they are host RAM exhaustion (no swap; free -m shows Swap 0), where the JVM could not commit native memory. That points to host-level overcommit, not backend.xmx. Root cause is tracked in SCALE-009 and SEC-004. Keep 8g, or go to 12g at most only after host memory is under control. | Y9: 2026-09-25 | Z9: Claude (AI-assisted review) - bundle dku_diagnosis_2026-07-22-08-21-05 (node p4d, DSS 14.4.3)
A10: SCALE-009 | B10: must_have | C10: specific_setting | D10: Flow Parallelism Limits | E10: Flow Limits Sizing (Max Jobs, Max Activities) | F10: Configure Flow concurrency limits using the 5-step sizing framework: reserve OS/backend.xmx memory, allocate roughly 70% of remaining memory to CGroups (less if offloading heavy workloads to EKS/Kubernetes), size Max Jobs from the remaining JEK memory, set the global Max Activities limit (30-50) as a backstop above Max Jobs, and leave Max Activities per Job at the default of 5. Max Jobs must never be set to 0, as this disables the limit entirely and risks crashing the instance via OOM. | G10: general-settings.json > maxRunningJobs | H10: not_equals | I10: 0 | K10: Also verify general-settings.json > maxRunningActivities falls within 30-50, and maxRunningActivitiesPerJob is at the default of 5 unless justified. Front-end equivalent: Administration > Settings > Resources control > Concurrent Activities. | L10: maxRunningJobs set to a positive nonzero value derived from the 5-step memory sizing framework; maxRunningActivities within 30-50; maxRunningActivitiesPerJob at 5 (or a justified alternative). | M10: maxRunningJobs is 0 or blank (critical stability risk); maxRunningActivities is outside 30-50 without justification; sizing doesn't account for available host memory, risking OOM. | N10: If these general-settings.json values are missing from the diagnosis, flag needs_manual_review and check the Administration > Settings > Resources control UI directly. | O10: Improperly sized flow limits risk instance-wide Out-Of-Memory crashes; Max Jobs=0 disables protection entirely. | P10: Flow limits, Max Jobs, Max Activities, CGroups, JEK, memory sizing | Q10: scalable_performance_ops | R10: 8, 9, 10, 11 | S10: Flow parallelism | MUST HAVE; Flow parallelism | MUST HAVE; Flow parallelism | MUST HAVE; Flow parallelism | MUST HAVE | T10: high | V10: Fail | W10: apps/dss/data_design/config/general-settings.json jekSettings.maxRunningJobs=0 (limit disabled; the same value was in general-settings.json_bkp from Oct 2024); maxRunningActivities=5; maxRunningActivitiesPerJob=5; maxRunningActivitiesPerKey=[]. Host: 62GB RAM, no swap, 8 cores; DSS cgroup 40G; backend 8g; JEKs 2g each and outside cgroups (SEC-005). hs_err_pid5201 (2026-03-28) and hs_err_pid2976607 (2026-07-21): native memory mmap failures; hs_err_pid1650445 (2025-12-23): JEK heap OOM. | X10: CRITICAL, and the likely root cause of the instability. Max running jobs = 0 means no limit. Each job spawns a 2GB-heap JEK that is not in any cgroup, so concurrent jobs can push the 62GB, no-swap host past physical RAM, on top of the 40G cgroup budget and the 8g backend. That matches the native-memory crash dumps (Mar and Jul 2026). Fix: set maxRunningJobs using the 5-step framework, e.g. 62GB - OS ~4GB - backend 8g ~ 50GB; about 70% to cgroups (~35-40G) leaves ~10-12GB for JEKs, so about 5 concurrent jobs at 2g. Raise maxRunningActivities to 30-50 only as a backstop above Max Jobs; the current value of 5 is well below the recommended band. Also offload recipes to K8s (ARCH-016) to cut host memory pressure. Linked: SEC-004, SCALE-008. | Y10: 2026-09-25 | Z10: Claude (AI-assisted review) - bundle dku_diagnosis_2026-07-22-08-21-05 (node p4d, DSS 14.4.3)
A11: SCALE-010 | B11: nice_to_have | C11: specific_setting | D11: Default Connection & Engine Preferences | E11: Preferred Connections and Engines Settings | F11: Default dataset creation settings and recipe engine preferences (preferedConnection, forcedPreferedConnection, preferedUploadConnection, preferedStorageFormats) are blank by default and should remain so unless a specific use case justifies setting them; in particular, preferred engine should almost always be left blank for v12+ instances since altering it can cause breaking changes. | G11: general-settings.json > defaultDatasetCreationSettings / recipeEnginesPreferences (preferedConnection, forcedPreferedConnection, preferedUploadConnection, preferedStorageFormats) | H11: equals | I11: unset/blank unless justified specific use case | K11: These keys may be entirely absent from general-settings.json if left blank, which is the expected default state. | L11: Keys absent or blank in general-settings.json, or if set, a documented specific use case justifies the value (e.g., not forcing storage to a local server). | M11: preferedConnection/forcedPreferedConnection set to force local server storage, or preferred engine changed without clear justification, especially on v12+ instances. | N11: If this section of general-settings.json is missing from the diagnosis, flag needs_manual_review and check the Administration > Settings > Engines & connections UI. | O11: These settings default to blank for good reason; forcing values can cause breaking changes or performance issues (e.g., forcing local storage). | P11: default dataset creation, recipe engine preferences, connections | Q11: scalable_performance_ops | R11: 12, 13, 14 | S11: Preferreds and Defaults | NICE TO HAVE; Preferreds and Defaults | NICE TO HAVE; Preferreds and Defaults | NICE TO HAVE | T11: medium | U11: Expected value is contextual ('reasonable values' if set), not a fixed constant, so the check requires judgment. | V11: Pass | W11: apps/dss/data_design/config/general-settings.json defaultDatasetCreationSettings: no preferedConnection/forcedPreferedConnection/preferedUploadConnection; preferedStorageFormats='CSV_ESCAPING_NOGZIP_FORHIVE,CSV_EXCEL_GZIP,PARQUET_HIVE' (unchanged since the Oct 2024 _bkp); recipeEnginesPreferences all empty (no forced or preferred engines). | X11: No forced connection and no engine preference: aligned with the v12+ guidance. The storage-format order is the standard list; leave it. | Y11: 2026-09-25 | Z11: Claude (AI-assisted review) - bundle dku_diagnosis_2026-07-22-08-21-05 (node p4d, DSS 14.4.3)
A12: SCALE-011 | B12: must_have | C12: specific_setting | D12: Connections Hygiene | E12: Remove filesystem_root Connection | F12: The default filesystem_root connection pointing to the server's root filesystem should be removed unless actively used by a project; if in use, propose a dedicated scoped connection to the specific path before removing filesystem_root. | G12: connections.json > filesystem_root | H12: not_exists | I12: removed (unless replaced by a scoped connection after confirming no active project usage) | K12: Check usage via Administration -> Monitoring before deletion. | L12: filesystem_root connection absent from the connections list, or confirmed unused and removed; if it was in use, a dedicated scoped connection was created to replace it. | M12: filesystem_root connection still present and either unused (should have been deleted) or in use without a safer scoped replacement. | N12: If the connections list isn't in the diagnosis, flag needs_manual_review and check the Administration > Connections UI directly. | O12: The filesystem_root connection exposes the entire server filesystem, posing a security and stability risk. | P12: connections, filesystem_root, security | Q12: scalable_performance_ops | R12: 14, 15 | S12: Remove filesystem_root connection | MUST HAVE; Remove filesystem_root connection | MUST HAVE | T12: high | V12: Fail | W12: apps/dss/data_design/config/connections.json: 'filesystem_root' (type Filesystem, params.root='/') present; usableBy=ALLOWED for Other_EDP_EAR-AA-20677_DSS_NP_ADMIN_local and Other_EDP_EAR-AA-20677_DSS_NP_DATA_SCIENTIST_Local; detailsReadability.readableBy=ALL. | X12: filesystem_root still exists. Access is limited to admin and data-scientist groups, which reduces the risk but still exposes the whole server filesystem. Check usage in Admin > Monitoring. If used, create a scoped connection to the specific path, migrate, then delete filesystem_root. | Y12: 2026-09-25 | Z12: Claude (AI-assisted review) - bundle dku_diagnosis_2026-07-22-08-21-05 (node p4d, DSS 14.4.3)
A13: SCALE-012 | B13: must_have | C13: specific_setting | D13: Cloud Storage Connections | E13: Cloud Object Storage Configuration (Details Readable By, HDFS Interface) | F13: For S3/Azure Blob/GCS connections, enable 'Details readable by' to allow compute engines (Spark, Snowflake, Databricks) direct/parallel access instead of funneling through the DSS node, and set the appropriate HDFS interface per cloud/storage type (S3: S3A off-EMR or EMRFS on-EMR; Azure Blob: ABFS if Hierarchical namespace enabled else WASB; GCS: GS). Consider S3 VPC endpoints if custom VPC egress routing impacts performance, though this should be a recommendation rather than a mandatory fix. | G13: cloud storage connection settings > detailsReadableBy | H13: equals | I13: enabled | K13: Also verify HDFS interface setting matches the cloud storage type mapping (S3A/EMRFS for S3, ABFS/WASB for Azure Blob, GS for GCS). | L13: Cloud storage connections show 'Details readable by' enabled and the correct HDFS interface configured per the platform/type mapping. | M13: 'Details readable by' disabled, forcing all traffic through the DSS node (performance bottleneck), or a mismatched/incorrect HDFS interface for the cloud storage type. | N13: If connection details aren't in the diagnosis, flag needs_manual_review and check Administration > Connections for each cloud storage connection. | O13: Without 'Details readable by', all data traffic funnels through the single DSS node creating a performance bottleneck; correct HDFS interface ensures compatibility with distributed compute engines. | P13: cloud storage connections, details readable by, HDFS interface, S3, Azure Blob, GCS | Q13: scalable_performance_ops | R13: 15, 16 | S13: Cloud Object Storage | MUST HAVE; Cloud Object Storage | MUST HAVE | T13: high | V13: Fail | W13: apps/dss/data_design/config/connections.json: ear27331_blob_stg_1 (Azure) detailsReadability=NONE, hdfsInterface=NONE; ear27026_blob_connection (Azure) readableBy=ALLOWED [admin group], hdfsInterface=NONE; ear21183_gcp_GCS_intermediate (GCS) readableBy=ALLOWED [ear-21183 designer/viewer], hdfsInterface=NONE. apps/dss/data_design/run/sanity-check.json: WARN_CONNECTION_SPARK_NO_GROUP_WITH_DETAILS_READ_ACCESS for ear27331_blob_stg_1. | X13: Spark is enabled and used, but one Azure connection has no details-readable groups (DSS itself warns), and none of the three cloud storage connections has an HDFS interface. Set GS for GCS, and ABFS (if hierarchical namespace is enabled) or WASB for Azure. Grant details-read to the groups that run Spark on these connections. | Y13: 2026-09-25 | Z13: Claude (AI-assisted review) - bundle dku_diagnosis_2026-07-22-08-21-05 (node p4d, DSS 14.4.3)
A14: SCALE-013 | B14: must_have | C14: specific_setting | D14: Cloud Data Warehouse Connections | E14: Snowflake Connection Configuration | F14: For Snowflake connections, confirm the cloud storage connection's authentication is compatible with Automatic fast-write, and enable Spark native integration, UDF support, and Automatic fast-write. 'Details readable by' on the cloud storage connection is required for Snowpark and Spark Native integration; without it, users are limited to Visual and SQL recipes. | G14: Snowflake connection settings > enableAutomaticFastWrite / enableSparkNativeIntegration / enableUDF, and cloud storage connection > detailsReadableBy | H14: equals | I14: enabled | K14: Cloud storage connection authentication must also meet the Automatic fast-write requirements per Dataiku documentation. | L14: Snowflake connection shows Automatic fast-write, Spark native integration, and UDF enabled where applicable, and the cloud storage connection has 'Details readable by' enabled with compatible auth. | M14: These settings disabled without justification, or cloud storage auth incompatible with fast-write requirements, limiting functionality (e.g., no Snowpark/Spark native access). | N14: If Snowflake connection settings aren't present in the diagnosis, flag needs_manual_review and check Administration > Connections for the Snowflake connection. | O14: These settings enable performant, parallel data movement and advanced compute integration (Snowpark, Spark) rather than slow single-threaded funneling. | P14: Snowflake, Automatic fast-write, Spark native integration, details readable by | Q14: scalable_performance_ops | R14: 16, 17 | S14: Snowflake | MUST HAVE; Snowflake | MUST HAVE | T14: high | V14: Not Applicable | W14: apps/dss/data_design/config/connections.json: no Snowflake connections (types: MySQL 15, SQLServer 9, AzureOpenAI 9, Oracle 4, Filesystem 3, BigQuery 2, AzureAISearch 2, Azure 2, GCS 1, VertexAILLM 1). | X14: There is no Snowflake connection. | Y14: 2026-09-25 | Z14: Claude (AI-assisted review) - bundle dku_diagnosis_2026-07-22-08-21-05 (node p4d, DSS 14.4.3)
A15: SCALE-014 | B15: must_have | C15: specific_setting | D15: Cloud Data Warehouse Connections | E15: Databricks Connection Configuration | F15: For Databricks connections, confirm the cloud storage connection's authentication is compatible with Automatic fast-write, and enable both Automatic fast-write and 'Details readable by' on the cloud storage connection. | G15: Databricks connection settings > enableAutomaticFastWrite, and cloud storage connection > detailsReadableBy | H15: equals | I15: enabled | K15: Cloud storage connection authentication must also meet the Automatic fast-write requirements per Dataiku documentation. | L15: Databricks connection shows Automatic fast-write enabled, and the cloud storage connection has 'Details readable by' enabled with compatible auth. | M15: Automatic fast-write or 'Details readable by' disabled, or cloud storage auth incompatible with fast-write requirements. | N15: If Databricks connection settings aren't present in the diagnosis, flag needs_manual_review and check Administration > Connections for the Databricks connection. | O15: These settings enable performant, parallel data movement between DSS and Databricks rather than slow single-threaded funneling. | P15: Databricks, Automatic fast-write, details readable by | Q15: scalable_performance_ops | R15: 17, 18 | S15: Databricks | MUST HAVE; Databricks | MUST HAVE | T15: high | V15: Not Applicable | W15: apps/dss/data_design/config/connections.json: no Databricks connections. | X15: There is no Databricks connection. | Y15: 2026-09-25 | Z15: Claude (AI-assisted review) - bundle dku_diagnosis_2026-07-22-08-21-05 (node p4d, DSS 14.4.3)
A16: SCALE-015 | B16: must_have | C16: specific_setting | D16: Cloud Data Warehouse Connections | E16: Amazon Redshift, Google BigQuery, Azure Synapse Connection Configuration | F16: For Redshift, BigQuery, and Synapse connections, confirm the cloud storage connection's authentication is compatible with Automatic fast-write, and enable Automatic fast-write. Note that for Redshift, the Fast Path only applies to writing to Redshift, not to unload operations. | G16: Redshift/BigQuery/Synapse connection settings > enableAutomaticFastWrite | H16: equals | I16: enabled | K16: Cloud storage connection authentication must also meet the Automatic fast-write requirements per Dataiku documentation; Redshift Fast Path is write-only and does not apply to unload. | L16: Redshift/BigQuery/Synapse connection shows Automatic fast-write enabled and compatible cloud storage authentication. | M16: Automatic fast-write disabled, or cloud storage auth incompatible with fast-write requirements. | N16: If these connection settings aren't present in the diagnosis, flag needs_manual_review and check Administration > Connections for the relevant connection. | O16: Automatic fast-write enables performant, parallel data movement rather than slow single-threaded funneling. | P16: Redshift, BigQuery, Synapse, Automatic fast-write | Q16: scalable_performance_ops | R16: 18 | S16: Amazon Redshift, Google BigQuery, Azure Synapse | MUST HAVE | T16: high | V16: Fail | W16: apps/dss/data_design/config/connections.json: BigQuery 'ear21183_gcp_big_query_intermediate' useAutoFastPath=false; BigQuery 'ear27554_bigquery' useAutoFastPath=false. A GCS connection exists (ear21183_gcp_GCS_intermediate, authType KEYPAIR) that could serve as the fast-path staging area. | X16: Automatic fast-write is off on both BigQuery connections, so writes go row-by-row through DSS. Enable it, pointing to a GCS connection with compatible auth (the ear21183 GCS connection is a natural pairing for ear21183 BigQuery). No Redshift or Synapse connections exist. | Y16: 2026-09-25 | Z16: Claude (AI-assisted review) - bundle dku_diagnosis_2026-07-22-08-21-05 (node p4d, DSS 14.4.3)
A17: SCALE-016 | B17: nice_to_have | C17: qualitative_practice | D17: Disaster Recovery & High Availability | E17: Disaster Recovery Strategy Discussion | F17: Discuss disaster recovery (DR) and high-availability (HA) considerations with the client based on the criticality of workloads: verify backup/snapshot scheduling against a defined RPO, existence of tested and possibly automated recovery procedures meeting RTO, and for active/passive HA setups, validate redundant identical servers without a common SPOF, shared/replicated storage, cluster/network failover management with fencing and a vanity/floating IP, and active monitoring/alerting (noting Dataiku does not provide monitoring). Do not commit to implementing a DR solution during the review sessions themselves. | L17: Documented backup/snapshot schedule meeting RPO, tested recovery/failover procedures meeting RTO, and for HA setups: redundant identical servers without shared SPOF, properly configured shared/replicated storage, cluster management with fencing, a vanity URL/floating IP, and active monitoring. | M17: No RPO/RTO defined, infrequent or untested backups, no documented recovery procedure, or HA setup missing key components (shared SPOF present, no fencing mechanism, no monitoring). | N17: If DR/HA plans are not discussed or documented in available materials, flag needs_manual_review and schedule a dedicated discussion with the client; do not commit to building a DR solution as part of the review itself. | O17: HA/DR planning ensures business continuity; horizontal HA is not natively possible for stateful DSS instances, making backup/recovery discipline critical. | P17: disaster recovery, high availability, RPO, RTO, failover | Q17: scalable_performance_ops | R17: 18, 19, 20 | S17: Disaster Recovery Strategy (Placeholder) | NICE TO HAVE; Disaster Recovery Strategy (Placeholder) | NICE TO HAVE; Disaster Recovery Strategy (Placeholder) | NICE TO HAVE | T17: medium | U17: Section heading is marked '(Placeholder)', suggesting the content may be incomplete or subject to revision in the source document. | V17: Needs Review | W17: No DR/HA material in the bundle. Single custom-install VM on GCP; H2 runtime DB; no backup evidence. | X17: Hold a dedicated DR/HA discussion covering RPO/RTO, snapshot schedule and restore testing. Note the H2 DB and single-VM setup. Do not commit to building DR during this review. | Y17: 2026-09-25 | Z17: Claude (AI-assisted review) - bundle dku_diagnosis_2026-07-22-08-21-05 (node p4d, DSS 14.4.3)

Sheet Advanced Security Options (DSS 
A1: id | B1: priority | C1: check_type | D1: subtopic | E1: title | F1: statement | G1: parameter_hint | H1: operator | I1: expected_value | J1: unit | K1: expected_condition_notes | L1: supporting_evidence | M1: contradicting_evidence | N1: insufficient_evidence_handling | O1: rationale | P1: dataiku_concepts | Q1: source_document | R1: source_page | S1: source_section | T1: confidence | U1: ambiguity_notes | V1: validation_status | W1: evidence_found | X1: notes | Y1: validated_at | Z1: validated_by
A2: ADVSEC-001 | B2: must_have | C2: specific_setting | D2: Information Disclosure Prevention | E2: Hiding error stacks | F2: By default, the DSS backend sends backend error stack traces to logged-in users to ease debugging; this can be disabled so that internal error details (file paths, internals, library versions) are not exposed to end users, by setting the security.hideErrorStacks key to true in general-settings.json. | G2: general-settings.json > security.hideErrorStacks | H2: equals | I2: true | L2: general-settings.json contains a "security" object with "hideErrorStacks": true. | M2: The "security" key is absent, or present without "hideErrorStacks", or it is explicitly set to false, meaning stack traces are still shown to logged-in users. | N2: If the diagnosis does not include the contents of general-settings.json, flag as needs_manual_review, since absence of the key means the DSS-shipped default (stack traces shown) applies. | O2: By default DSS sends backend error stacks to logged-in users to make debugging and understanding easier; this can be turned off to prevent internal implementation details from leaking to users. | P2: general-settings.json, security settings, error handling | Q2: advanced_security_options | R2: 1, 2 | S2: Hiding error stacks; Hiding error stacks | T2: high | V2: Fail | W2: apps/dss/data_design/config/general-settings.json security.hideErrorStacks=false. | X2: Stack traces are shown to logged-in users. Set security.hideErrorStacks=true. | Y2: 2026-09-25 | Z2: Claude (AI-assisted review) - bundle dku_diagnosis_2026-07-22-08-21-05 (node p4d, DSS 14.4.3)
A3: ADVSEC-002 | B3: nice_to_have | C3: specific_setting | D3: Information Disclosure Prevention | E3: Hiding version info | F3: By default, the DSS backend sends DSS version information even to non-logged-in users; this can be suppressed by setting security.hideVersionStringsWhenNotLogged to true in general-settings.json. | G3: general-settings.json > security.hideVersionStringsWhenNotLogged | H3: equals | I3: true | L3: general-settings.json "security" object contains "hideVersionStringsWhenNotLogged": true. | M3: The key is absent or set to false, meaning version info is still sent to non-logged-in users. | N3: If general-settings.json content is not present in the diagnosis, flag as needs_manual_review; the default (version info exposed) applies absent this key. | O3: By default DSS sends version information even to non-logged in users; this can be disabled to reduce fingerprinting of the DSS instance. | P3: general-settings.json, security settings, version disclosure | Q3: advanced_security_options | R3: 2 | S3: Hiding version info | T3: high | V3: Fail | W3: apps/dss/data_design/config/general-settings.json security.hideVersionStringsWhenNotLogged=false. | X3: The DSS version is exposed to unauthenticated users. Set it to true to reduce fingerprinting. | Y3: 2026-09-25 | Z3: Claude (AI-assisted review) - bundle dku_diagnosis_2026-07-22-08-21-05 (node p4d, DSS 14.4.3)
A4: ADVSEC-003 | B4: nice_to_have | C4: specific_setting | D4: Cookie & Transport Security | E4: Using secure cookies | F4: By default, DSS login cookies do not carry the Secure flag, meaning they could be sent over unencrypted HTTP. Where HTTPS is used for all users (natively or via reverse proxy), administrators should set security.secureCookies to true in general-settings.json so that session cookies are only ever transmitted over secure connections, enhancing session security. | G4: general-settings.json > security.secureCookies | H4: equals | I4: true | K4: Should only be enabled once DSS is served exclusively over HTTPS everywhere (natively or via reverse proxy); enabling without full HTTPS coverage would break login for HTTP-only clients. | L4: general-settings.json shows secureCookies: true under the security top-level section, ideally alongside evidence that DSS/its reverse proxy enforces HTTPS for all users. | M4: secureCookies is false or absent while HTTPS is confirmed used for all users, or secureCookies is true without any HTTPS confirmation. | N4: If HTTPS usage status or the general-settings.json security section is not visible in the diagnosis file, flag as needs_manual_review. | O4: Secure cookies prevent cookies from being transmitted over unencrypted connections, reducing session hijacking risk when HTTPS is in use; they ensure the browser never sends the session cookie over unsecured connections, further securing user sessions. | P4: secure cookies, general-settings.json, security settings, cookies, HTTPS | Q4: advanced_security_options, security_permissions_compliance | R4: 6, 7, 2, 3 | S4: Secure Cookies | NICE TO HAVE; Secure Cookies | NICE TO HAVE (Review steps); Using secure cookies; Using secure cookies | T4: low | U4: Source documents disagree on priority: the security_permissions_compliance document explicitly tags this NICE TO HAVE, while the advanced_security_options document treats it as must_have via inferred reasoning about session-security hardening. Per merge policy, the explicit_in_source classification (nice_to_have) was retained; downstream reviewers should be aware of this discrepancy when weighing severity. | V4: Fail | W4: apps/dss/data_design/config/general-settings.json security.secureCookies=false, while access is via HTTPS (studioExternalUrl https://design.ds.p4d.data.slb.com; HSTS set in install.ini). | X4: HTTPS is in use (see SEC-006), but session cookies lack the Secure flag. Once plain HTTP access is confirmed closed, set secureCookies=true. | Y4: 2026-09-25 | Z4: Claude (AI-assisted review) - bundle dku_diagnosis_2026-07-22-08-21-05 (node p4d, DSS 14.4.3)
A5: ADVSEC-004 | B5: must_have | C5: specific_setting | D5: Session Management | E5: Expiring sessions | F5: DSS can be configured to expire user sessions after a maximum duration since login and/or after a period of inactivity, via Administration > Settings > Security & Audit > User login & provisioning > Session management ('Maximum session duration' and 'Idle timeout'), noting this can cause lost work if a session expires mid-edit. | G5: Administration > Settings > Security & Audit > User login & provisioning > Session management > Maximum session duration / Idle timeout | H5: exists | I5: configured to a finite, non-default timeout value | K5: The source does not mandate a specific numeric threshold, only that admins may configure these fields; treat as satisfied if either or both values are set to a finite duration rather than left unlimited/unset. | L5: Diagnosis or exported settings show a configured, finite 'Maximum session duration' and/or 'Idle timeout' value in session management settings. | M5: Session management settings show these fields unset or set to unlimited/no-expiration. | N5: Session management configuration is often not captured in standard diagnostic exports (it's a UI/DB-stored setting, not a config file key); flag as needs_manual_review, noting the source's own caveat about potential lost work from expiring sessions. | O5: Session expiration limits how long a stolen or abandoned session remains valid, though the source warns it can cause lost in-progress work (including complications with open Jupyter notebooks). | P5: session management, user login & provisioning | Q5: advanced_security_options | R5: 3 | S5: Expiring sessions | T5: medium | U5: No literal config-file key is given for this UI-only setting, and no specific recommended numeric threshold is provided, so the expected_condition is a best-effort conceptual pointer to the UI path rather than a literal field. | V5: Fail | W5: apps/dss/data_design/config/general-settings.json security.sessionsMaxTotalTimeMinutes=0 and sessionsMaxIdleTimeMinutes=0 (no expiry); persistSessionsOnDisk=true. | X5: Sessions never expire. Set a finite idle timeout and/or maximum duration (e.g. 8-12h max, 60-120 min idle), and warn users about possible loss of unsaved work in Jupyter. | Y5: 2026-09-25 | Z5: Claude (AI-assisted review) - bundle dku_diagnosis_2026-07-22-08-21-05 (node p4d, DSS 14.4.3)
A6: ADVSEC-005 | B6: must_have | C6: specific_setting | D6: Session Management | E6: Forcing a single session per user | F6: By default DSS allows a user to be logged in from multiple sessions simultaneously; administrators can enable 'Force single session per user' (Administration > Settings > Security & Audit > User login & provisioning > Session management) so that a new login terminates all of that user's other active sessions. | G6: Administration > Settings > Security & Audit > User login & provisioning > Session management > Force single session per user | H6: equals | I6: enabled | K6: This is a UI toggle, not a documented general-settings.json/dip.properties key in the source text. | L6: Session management settings show 'Force single session per user' enabled. | M6: The setting is shown as disabled (default), allowing multiple concurrent sessions per user. | N6: This UI-only toggle is often not captured in diagnostic exports; flag as needs_manual_review, noting the default is disabled (multiple sessions allowed). | O6: By default users can have multiple simultaneous sessions; forcing a single session per user terminates other sessions on new login, reducing exposure from stale or hijacked sessions. | P6: session management, user login & provisioning | Q6: advanced_security_options | R6: 3 | S6: Forcing a single session per user | T6: medium | U6: No literal config-file key is given for this UI-only setting. | V6: Fail | W6: apps/dss/data_design/config/general-settings.json security.forceSingleSessionPerUser=false. | X6: Multiple concurrent sessions per user are allowed (the default). Enable 'Force single session per user' if it fits how users work. | Y6: 2026-09-25 | Z6: Claude (AI-assisted review) - bundle dku_diagnosis_2026-07-22-08-21-05 (node p4d, DSS 14.4.3)
A7: ADVSEC-006 | B7: nice_to_have | C7: specific_setting | D7: User Isolation Framework | E7: Restricting visibility of groups and users | F7: By default, all logged-in DSS users can view the full list of groups and users (useful for adding groups to projects and mentioning users); administrators can set security.restrictUsersAndGroupsVisibility to true in general-settings.json to limit visibility to admins, one's own groups/their members, and users who share a project, though this is explicitly a best-effort feature without a guarantee of perfect isolation. | G7: general-settings.json > security.restrictUsersAndGroupsVisibility | H7: equals | I7: true | K7: Best-effort feature; does not guarantee full isolation and reduces convenience features like universal user mentions and easy group-adding for project owners, so instances may deliberately leave it disabled. | L7: general-settings.json "security" object contains "restrictUsersAndGroupsVisibility": true. | M7: The key is absent or false, meaning all logged-in users can see the full list of groups and users. | N7: If general-settings.json content is not present in the diagnosis, flag as needs_manual_review; the default (unrestricted visibility) applies absent this key. | O7: Restricting visibility of the global user/group list can reduce information available for social-engineering/enumeration, though the source notes it is best-effort and does not guarantee full isolation. | P7: general-settings.json, security settings, user/group visibility | Q7: advanced_security_options | R7: 3, 4 | S7: Restricting visibility of groups and users; Restricting visibility of groups and users | T7: high | U7: Note: despite the subtopic label 'User Isolation Framework' shared with SEC-002, this setting concerns UI-level visibility of the group/user directory and is a distinct checkable practice from the OS-level impersonation-based User Isolation Framework covered in SEC-002. | V7: Fail | W7: apps/dss/data_design/config/general-settings.json security.restrictUsersAndGroupsVisibility=false. | X7: All users can list every user and group. Consider enabling it, given the multi-tenant per-EAR group model; it is best-effort only. | Y7: 2026-09-25 | Z7: Claude (AI-assisted review) - bundle dku_diagnosis_2026-07-22-08-21-05 (node p4d, DSS 14.4.3)
A8: ADVSEC-007 | B8: nice_to_have | C8: specific_setting | D8: Session & Logout UX | E8: Redirecting to a custom URL after logout | F8: By default, users are redirected to a standard DSS-hosted page after logout; administrators can configure security.postLogoutBehavior (CUSTOM_URL for a GET redirect or CUSTOM_URL_POST for a POST request aligned with OpenID Connect RP-Initiated Logout) together with security.postLogoutCustomURL (must be an http/https URL) in general-settings.json to redirect users elsewhere, with DSS validating these settings on save/load and falling back to the default page on invalid values. | G8: general-settings.json > security.postLogoutBehavior / security.postLogoutCustomURL | H8: one_of | I8: CUSTOM_URL, CUSTOM_URL_POST | K8: postLogoutCustomURL is required and must be an http/https URL when postLogoutBehavior is CUSTOM_URL or CUSTOM_URL_POST; DSS validates these settings on save and on load, falling back to the default DSS logged-out page if invalid. | L8: general-settings.json "security" object contains postLogoutBehavior set to CUSTOM_URL or CUSTOM_URL_POST along with a valid http/https postLogoutCustomURL. | M8: The keys are absent (default DSS logged-out page used) or postLogoutCustomURL is invalid, in which case DSS falls back to default behavior anyway. | N8: If general-settings.json content is not present in the diagnosis, flag as needs_manual_review; absence means the default logout page is used, which is not a security concern. | O8: Allows organizations to redirect users to a branded or external page after logout instead of the DSS default logged-out page. | P8: general-settings.json, security settings, logout, OpenID Connect | Q8: advanced_security_options | R8: 4, 5 | S8: Redirecting to a custom URL after logout; Redirecting to a custom URL after logout | T8: high | V8: Fail | W8: apps/dss/data_design/config/general-settings.json security.postLogoutBehavior='LOGGED_OUT_PAGE'; no postLogoutCustomURL. | X8: Low risk: the default logout page is used. With Azure AD OIDC SSO, CUSTOM_URL_POST to the IdP end-session endpoint would give a proper RP-initiated logout. This is optional. | Y8: 2026-09-25 | Z8: Claude (AI-assisted review) - bundle dku_diagnosis_2026-07-22-08-21-05 (node p4d, DSS 14.4.3)
A9: ADVSEC-008 | B9: must_have | C9: specific_setting | D9: Content Upload Restrictions | E9: Restricting types of files that can be uploaded in wikis | F9: By default, all logged-in DSS users can upload any type of file to wiki articles; administrators can restrict this by setting dku.wikis.authorizedUploadExtensions in dip.properties to a comma-separated allow-list of file extensions (e.g., png,jpg,jpeg,gif,txt,csv). | G9: dip.properties > dku.wikis.authorizedUploadExtensions | H9: exists | I9: restricted list of extensions (e.g., png,jpg,jpeg,gif,txt,csv) | K9: Default (unset) allows uploads of any file type; presence of this key with a restrictive list indicates the practice is followed. | L9: dip.properties contains dku.wikis.authorizedUploadExtensions set to a specific, restrictive comma-separated list of extensions. | M9: The key is absent from dip.properties, meaning any file type can be uploaded to wiki articles. | N9: If dip.properties content is not present in the diagnosis, flag as needs_manual_review; the default (unrestricted upload types) applies absent this key. | O9: Restricting file types uploaded to wikis reduces the risk of malicious or unwanted file types being hosted and shared via the DSS wiki feature. | P9: dip.properties, wikis, file upload restrictions | Q9: advanced_security_options | R9: 6 | S9: Restricting types of files that can be uploaded in wikis | T9: high | V9: Fail | W9: apps/dss/data_design/config/dip.properties has no dku.wikis.authorizedUploadExtensions (the file contains only logging.limit.* and dku.scenarios.triggers.* keys). | X9: Any file type can be uploaded to wikis. Add dku.wikis.authorizedUploadExtensions=png,jpg,jpeg,gif,txt,csv (adjust as needed) and restart. | Y9: 2026-09-25 | Z9: Claude (AI-assisted review) - bundle dku_diagnosis_2026-07-22-08-21-05 (node p4d, DSS 14.4.3)
A10: ADVSEC-009 | B10: must_have | C10: specific_setting | D10: Data Exfiltration Controls | E10: Restricting exports | F10: DSS can globally restrict export/copy features (regardless of project-level permissions) via a set of escalating dip.properties keys: disableAllDatasetExports, disableAllDataExports (implies the former), disableAllExports (implies both former), plus the independent disableCopySampleToClipboard and disableSQLNotebookCopyResultToClipboard keys for clipboard copying; the source explicitly warns this is only a 'best-effort' restriction since any user who can see data can still exfiltrate it, e.g. via copy/paste. | G10: dip.properties > dku.exports.disable* | H10: one_of | I10: dku.exports.disableAllDatasetExports=true; dku.exports.disableAllDataExports=true; dku.exports.disableAllExports=true; dku.exports.disableCopySampleToClipboard=true; dku.exports.disableSQLNotebookCopyResultToClipboard=true | K10: dku.exports.disableAllDatasetExports=true disables 'Download' export of datasets to files (CSV, Excel, Tableau Hyper, etc.), plus including datasets in project exports/bundle downloads and attaching datasets to emails in scenarios; other exports (ML data, schema, SQL queries, prepared data) remain possible. dku.exports.disableAllDataExports=true implies the previous key and additionally disables exports of prepared data or SQL query results, downloading files/zips from managed folders, and including datasets or managed folders in project exports/bundle downloads or scenario email attachments; ML data and schema exports remain possible. dku.exports.disableAllExports=true implies both previous keys and additionally disables exports of ML data and schemas, so essentially all dataset, prepared-data, SQL-query, ML data/schema, and managed-folder exports, downloads, bundle inclusions, and email attachments are disabled. dku.exports.disableCopySampleToClipboard=true disables copying data samples to the clipboard everywhere except SQL notebooks (default false, i.e. enabled). dku.exports.disableSQLNotebookCopyResultToClipboard=true disables copying results to the clipboard specifically in SQL notebooks (default false, i.e. enabled). | L10: dip.properties contains one or more of the five dku.exports.disable* keys set to true, at a scope level (dataset/data/all) matching the organization's data-exfiltration risk tolerance. | M10: None of the dku.exports.disable* keys are present or set to true, meaning full export and clipboard-copy capabilities remain available to any user with data-view permission. | N10: dip.properties content is often not fully captured in diagnostics; if absent, flag as needs_manual_review. Importantly, even when these settings are enabled, treat this only as a risk-reduction control, not a guarantee: the source explicitly states export restriction is inherently 'best-effort' since a user who can view data can still exfiltrate it by other means (e.g., copy/paste). | O10: Restricting export and clipboard-copy features reduces (but per the source's own warning, does not eliminate) the ability of authorized viewers to exfiltrate data out of DSS. | P10: dip.properties, exports, data exfiltration | Q10: advanced_security_options | R10: 6, 7, 8 | S10: Restricting exports; Restricting exports; Restricting exports | T10: high | V10: Fail | W10: apps/dss/data_design/config/dip.properties has no dku.exports.disable* keys. | X10: All export and clipboard features are available. Decide the scope with the data owners (e.g. dku.exports.disableAllDatasetExports=true instance-wide if data sensitivity warrants it). This is a best-effort control only. | Y10: 2026-09-25 | Z10: Claude (AI-assisted review) - bundle dku_diagnosis_2026-07-22-08-21-05 (node p4d, DSS 14.4.3)
A11: ADVSEC-010 | B11: must_have | C11: specific_setting | D11: Transport & Browser Hardening | E11: Setting security-related HTTP headers | F11: DSS supports configuring standard security-related HTTP response headers (X-Frame-Options, Content-Security-Policy, X-XSS-Protection, X-Content-Type-Options, Strict-Transport-Security, Referrer-Policy, Permissions-Policy, Cross-Origin-Embedder-Policy, Cross-Origin-Opener-Policy, Cross-Origin-Resource-Policy) in the [server] section of install.ini, requiring a `dssadmin regenerate-config` run and a DSS restart to take effect. | G11: install.ini > [server] content-security-policy / x-frame-options / x-content-type-options / x-xss-protection / hsts-max-age / referrer-policy / permissions-policy / cross-origin-embedder-policy / cross-origin-opener-policy / cross-origin-resource-policy | H11: exists | I11: restrictive values configured for each applicable header (e.g., x-frame-options=SAMEORIGIN, x-content-type-options=nosniff, hsts-max-age set to a non-zero value, a content-security-policy restricting sources) | K11: The source provides an example syntax but does not mandate one canonical value set for every header; presence of a restrictive, deliberately-chosen value for each relevant header indicates the practice is followed. | L11: install.ini's [server] section contains one or more of these header keys with restrictive values (e.g., SAMEORIGIN/DENY for x-frame-options, nosniff for x-content-type-options, a non-trivial content-security-policy, hsts-max-age set). | M11: The [server] section lacks these header keys entirely, meaning DSS is not emitting these security headers (browser defaults/no explicit protection). | N11: install.ini is a server-level config file often not captured in diagnostics; if absent, flag as needs_manual_review, since the default state (no headers configured) cannot otherwise be confirmed. | O11: Configuring these headers hardens the DSS Web application against clickjacking, XSS, MIME-sniffing, protocol downgrade, and cross-origin data leakage attacks. | P11: install.ini, HTTP security headers, CSP, HSTS | Q11: advanced_security_options | R11: 8 | S11: Setting security-related HTTP headers | T11: high | V11: Pass | W11: apps/dss/data_design/install.ini [server]: content-security-policy="script-src 'self' 'unsafe-inline' 'unsafe-eval'; frame-ancestors 'none'", x-frame-options=SAMEORIGIN, x-content-type-options=nosniff, x-xss-protection=1;mode=block, hsts-max-age=31536000, referrer-policy=same-origin. | X11: The core security headers are set. Improvements: the CSP allows 'unsafe-inline'/'unsafe-eval' in script-src; permissions-policy and cross-origin-embedder/opener/resource-policy are not set. Also, x-frame-options=SAMEORIGIN is looser than CSP frame-ancestors 'none'; align them. | Y11: 2026-09-25 | Z11: Claude (AI-assisted review) - bundle dku_diagnosis_2026-07-22-08-21-05 (node p4d, DSS 14.4.3)
A12: ADVSEC-011 | B12: nice_to_have | C12: specific_setting | D12: Embedding & Cookie Policy Tradeoffs | E12: Allowing DSS to be hosted inside an iframe | F12: By default DSS cannot be embedded in an iframe because browsers treat its authentication cookies as SameSite=Lax; enabling iframe embedding requires setting both security.sameSiteNoneCookies and security.secureCookies to true in general-settings.json, and requires DSS to be accessed exclusively via HTTPS (since browsers ignore SameSite=None on non-secure cookies). | G12: general-settings.json > security.sameSiteNoneCookies | H12: equals | I12: false (secure default) unless a documented iframe-embedding need exists | K12: If enabled, security.secureCookies must also be true and DSS must be served exclusively over HTTPS; sameSiteNoneCookies=true without a documented business need for iframe embedding is a red flag. | L12: general-settings.json "security" object omits sameSiteNoneCookies or sets it to false (secure default preserved). | M12: sameSiteNoneCookies is set to true without secureCookies also being true and/or without confirmed exclusive HTTPS access, or is enabled with no documented iframe-embedding justification. | N12: If general-settings.json's security block is not present in the diagnosis, flag as needs_manual_review; the default assumption (disabled, DSS not embeddable) applies absent this key. | O12: Allowing iframe embedding is only intended for specific integration scenarios; enabling it relaxes a cookie protection browsers use to mitigate certain cross-site attack vectors, so it should be a deliberate, justified choice. | P12: general-settings.json, security settings, cookies, iframe embedding, SameSite | Q12: advanced_security_options | R12: 8, 9 | S12: Allowing DSS to be hosted inside an iframe; Allowing DSS to be hosted inside an iframe | T12: high | V12: Pass | W12: apps/dss/data_design/config/general-settings.json security.sameSiteNoneCookies=false. | X12: The secure default is kept, and DSS cannot be embedded in an iframe. | Y12: 2026-09-25 | Z12: Claude (AI-assisted review) - bundle dku_diagnosis_2026-07-22-08-21-05 (node p4d, DSS 14.4.3)
A13: ADVSEC-012 | B13: nice_to_have | C13: specific_setting | D13: Content Rendering Hardening | E13: Preventing links to be clickable in data tables | F13: By default, DSS renders links as clickable in dataset Explore and dataset insights views; this can be disabled by setting dku.feature.dataTableLinks.enabled to false in dip.properties, preventing users from clicking potentially malicious or phishing links embedded within data content. | G13: dip.properties > dku.feature.dataTableLinks.enabled | H13: equals | I13: false | L13: dip.properties contains dku.feature.dataTableLinks.enabled=false. | M13: The key is absent (default true) or explicitly set to true, meaning links in data tables remain clickable. | N13: If dip.properties content is not present in the diagnosis, flag as needs_manual_review; the default (links clickable) applies absent this key. | O13: Disabling clickable links in dataset Explore/insights reduces the risk that a malicious or phishing link embedded in data content could be inadvertently clicked by a user. | P13: dip.properties, dataset explore, phishing mitigation | Q13: advanced_security_options | R13: 9 | S13: Preventing links to be clickable in data tables | T13: high | V13: Fail | W13: apps/dss/data_design/config/dip.properties has no dku.feature.dataTableLinks.enabled key; apps/dss/data_design/config/general-settings.json security.disableDataTableLinks=false. | X13: Links in data tables are clickable (the default). Set dku.feature.dataTableLinks.enabled=false (or security.disableDataTableLinks=true) to reduce phishing risk. | Y13: 2026-09-25 | Z13: Claude (AI-assisted review) - bundle dku_diagnosis_2026-07-22-08-21-05 (node p4d, DSS 14.4.3)
A14: ADVSEC-013 | B14: nice_to_have | C14: specific_setting | D14: Identity Integrity & Impersonation Prevention | E14: Allowing DSS users to edit their display names and emails | F14: Since DSS 13.2.0, only administrators can edit users' display names and email addresses by default, specifically to prevent impersonation; enabling security.enableEmailAndDisplayNameModification (true) in general-settings.json lets users self-service these fields but also disables the ability for users to share assets (e.g., projects) via email invitations, so DSS should not have this enabled unless there is a specific, documented business need. | G14: general-settings.json > security.enableEmailAndDisplayNameModification | H14: equals | I14: false (secure default) unless documented otherwise | K14: If true, email-invitation-based asset sharing (e.g., project sharing via email invite) is disabled as a side effect; enabling should only be done for a specific, documented business need. | L14: general-settings.json "security" object omits enableEmailAndDisplayNameModification or sets it to false, meaning only admins can edit user display names/emails (impersonation risk minimized). | M14: enableEmailAndDisplayNameModification is set to true without a documented business justification, allowing users to self-service edit their display name/email (impersonation risk, and email-invitation sharing disabled). | N14: If general-settings.json's security block is not present in the diagnosis, flag as needs_manual_review; the post-13.2.0 default (self-edit disabled) should be assumed absent evidence otherwise. | O14: This restriction (default since 13.2.0) helps prevent impersonation by DSS users; enabling self-edit trades that protection for convenience and disables the email-invitation sharing feature. | P14: general-settings.json, security settings, user identity, impersonation prevention, sharing | Q14: advanced_security_options | R14: 9, 10 | S14: Allowing DSS users to edit their display names and emails; Allowing DSS users to edit their display names and emails | T14: high | V14: Pass | W14: apps/dss/data_design/config/general-settings.json security.enableEmailAndDisplayNameModification=false. | X14: The secure default is kept: only admins can change display names and emails. | Y14: 2026-09-25 | Z14: Claude (AI-assisted review) - bundle dku_diagnosis_2026-07-22-08-21-05 (node p4d, DSS 14.4.3)
